{ "accidents" : [
{ "lat": 46.240000, "lng": 1.490000, "grv": "#f6ff00" },
{ "lat": 46.144000, "lng": 1.921000, "grv": "#f6ff00" },
{ "lat": 46.308000, "lng": 1.665000, "grv": "#f6ff00" },
{ "lat": 46.409000, "lng": 1.849000, "grv": "#f6ff00" },
{ "lat": 46.165000, "lng": 1.894000, "grv": "#f6ff00" },
{ "lat": 46.175000, "lng": 1.814000, "grv": "#f6ff00" },
{ "lat": 46.175000, "lng": 1.813000, "grv": "#f6ff00" },
{ "lat": 46.005000, "lng": 1.725000, "grv": "#f6ff00" },
{ "lat": 46.113000, "lng": 1.984000, "grv": "#f6ff00" },
{ "lat": 46.332000, "lng": 1.905000, "grv": "#f6ff00" },
{ "lat": 46.985000, "lng": 1.610000, "grv": "#f6ff00" },
{ "lat": 46.595000, "lng": 1.521000, "grv": "#f6ff00" },
{ "lat": 46.790000, "lng": 1.480000, "grv": "#f6ff00" },
{ "lat": 46.890000, "lng": 1.480000, "grv": "#f6ff00" },
{ "lat": 46.900000, "lng": 1.450000, "grv": "#f6ff00" },
{ "lat": 46.804000, "lng": 1.645000, "grv": "#f6ff00" },
{ "lat": 46.983000, "lng": 1.614000, "grv": "#f6ff00" },
{ "lat": 46.913000, "lng": 1.899000, "grv": "#f6ff00" },
{ "lat": 46.811000, "lng": 1.301000, "grv": "#f6ff00" },
{ "lat": 46.894000, "lng": 1.426000, "grv": "#f6ff00" },
{ "lat": 46.741000, "lng": 1.007000, "grv": "#f6ff00" },
{ "lat": 46.534000, "lng": 1.920000, "grv": "#f6ff00" },
{ "lat": 46.560000, "lng": 1.866000, "grv": "#f6ff00" },
{ "lat": 46.632000, "lng": 1.067000, "grv": "#f6ff00" },
{ "lat": 46.802000, "lng": 1.752000, "grv": "#f6ff00" },
{ "lat": 46.578000, "lng": 1.996000, "grv": "#f6ff00" },
{ "lat": 46.693000, "lng": 1.896000, "grv": "#f6ff00" },
{ "lat": 46.804000, "lng": 1.032000, "grv": "#f6ff00" },
{ "lat": 46.939000, "lng": 1.322000, "grv": "#f6ff00" },
{ "lat": 46.971000, "lng": 1.203000, "grv": "#f6ff00" },
{ "lat": 46.592000, "lng": 1.520000, "grv": "#f6ff00" },
{ "lat": 46.891000, "lng": 1.417000, "grv": "#f6ff00" },
{ "lat": 46.640000, "lng": 1.065000, "grv": "#f6ff00" },
{ "lat": 46.455000, "lng": 1.650000, "grv": "#f6ff00" },
{ "lat": 46.945000, "lng": 1.233000, "grv": "#f6ff00" },
{ "lat": 46.584000, "lng": 1.982000, "grv": "#f6ff00" },
{ "lat": 46.446000, "lng": 1.597000, "grv": "#f6ff00" },
{ "lat": 46.691000, "lng": 1.584000, "grv": "#f6ff00" },
{ "lat": 46.628000, "lng": 1.490000, "grv": "#f6ff00" },
{ "lat": 46.770000, "lng": 1.470000, "grv": "#f6ff00" },
{ "lat": 46.706000, "lng": 1.235000, "grv": "#f6ff00" },
{ "lat": 46.587000, "lng": 1.991000, "grv": "#f6ff00" },
{ "lat": 46.602000, "lng": 1.733000, "grv": "#f6ff00" },
{ "lat": 46.607000, "lng": 1.691000, "grv": "#f6ff00" },
{ "lat": 46.633000, "lng": 1.065000, "grv": "#f6ff00" },
{ "lat": 46.907000, "lng": 1.883000, "grv": "#f6ff00" },
{ "lat": 46.579000, "lng": 1.499000, "grv": "#f6ff00" },
{ "lat": 46.850000, "lng": 1.542000, "grv": "#f6ff00" },
{ "lat": 46.638000, "lng": 1.104000, "grv": "#f6ff00" },
{ "lat": 46.836000, "lng": 1.863000, "grv": "#f6ff00" },
{ "lat": 46.917000, "lng": 1.643000, "grv": "#f6ff00" },
{ "lat": 46.385000, "lng": 1.449000, "grv": "#f6ff00" },
{ "lat": 46.812000, "lng": 1.157000, "grv": "#f6ff00" },
{ "lat": 46.534000, "lng": 1.508000, "grv": "#f6ff00" },
{ "lat": 46.577000, "lng": 1.536000, "grv": "#f6ff00" },
{ "lat": 46.900000, "lng": 1.426000, "grv": "#f6ff00" },
{ "lat": 46.987000, "lng": 1.972000, "grv": "#f6ff00" },
{ "lat": 46.944000, "lng": 1.942000, "grv": "#f6ff00" },
{ "lat": 46.955000, "lng": 1.992000, "grv": "#f6ff00" },
{ "lat": 46.637000, "lng": 1.024000, "grv": "#f6ff00" },
{ "lat": 46.848000, "lng": 1.902000, "grv": "#f6ff00" },
{ "lat": 46.593000, "lng": 1.520000, "grv": "#f6ff00" },
{ "lat": 46.620000, "lng": 1.070000, "grv": "#f6ff00" },
{ "lat": 46.822000, "lng": 1.267000, "grv": "#f6ff00" },
{ "lat": 46.831000, "lng": 1.828000, "grv": "#f6ff00" },
{ "lat": 46.640000, "lng": 1.290000, "grv": "#f6ff00" },
{ "lat": 46.946000, "lng": 1.322000, "grv": "#f6ff00" },
{ "lat": 46.942000, "lng": 1.919000, "grv": "#f6ff00" },
{ "lat": 46.601000, "lng": 1.809000, "grv": "#f6ff00" },
{ "lat": 46.429000, "lng": 1.717000, "grv": "#f6ff00" },
{ "lat": 46.560000, "lng": 1.569000, "grv": "#f6ff00" },
{ "lat": 46.600000, "lng": 1.577000, "grv": "#f6ff00" },
{ "lat": 46.849000, "lng": 1.539000, "grv": "#f6ff00" },
{ "lat": 46.925000, "lng": 1.127000, "grv": "#f6ff00" },
{ "lat": 46.959000, "lng": 1.994000, "grv": "#f6ff00" },
{ "lat": 46.827000, "lng": 1.911000, "grv": "#f6ff00" },
{ "lat": 46.914000, "lng": 1.343000, "grv": "#f6ff00" },
{ "lat": 46.551000, "lng": 1.594000, "grv": "#f6ff00" },
{ "lat": 46.608000, "lng": 1.509000, "grv": "#f6ff00" },
{ "lat": 46.461000, "lng": 1.889000, "grv": "#f6ff00" },
{ "lat": 46.739000, "lng": 1.407000, "grv": "#f6ff00" },
{ "lat": 46.734000, "lng": 1.611000, "grv": "#f6ff00" },
{ "lat": 46.896000, "lng": 1.431000, "grv": "#f6ff00" },
{ "lat": 46.579000, "lng": 1.977000, "grv": "#f6ff00" },
{ "lat": 46.775800, "lng": 1.648550, "grv": "#f6ff00" },
{ "lat": 46.540900, "lng": 1.145790, "grv": "#f6ff00" },
{ "lat": 46.803400, "lng": 1.707820, "grv": "#f6ff00" },
{ "lat": 46.803560, "lng": 1.653540, "grv": "#f6ff00" },
{ "lat": 46.995200, "lng": 1.915800, "grv": "#f6ff00" },
{ "lat": 46.808900, "lng": 1.680740, "grv": "#f6ff00" },
{ "lat": 46.814200, "lng": 1.661340, "grv": "#f6ff00" },
{ "lat": 46.805400, "lng": 1.687170, "grv": "#f6ff00" },
{ "lat": 46.771100, "lng": 1.591540, "grv": "#f6ff00" },
{ "lat": 46.782600, "lng": 1.675840, "grv": "#f6ff00" },
{ "lat": 46.815200, "lng": 1.696760, "grv": "#f6ff00" },
{ "lat": 46.805000, "lng": 1.697970, "grv": "#f6ff00" },
{ "lat": 46.851500, "lng": 1.703400, "grv": "#f6ff00" },
{ "lat": 46.723700, "lng": 1.534530, "grv": "#f6ff00" },
{ "lat": 46.633600, "lng": 1.427820, "grv": "#f6ff00" },
{ "lat": 46.816700, "lng": 1.697090, "grv": "#f6ff00" },
{ "lat": 46.890400, "lng": 1.853540, "grv": "#f6ff00" },
{ "lat": 46.808900, "lng": 1.704810, "grv": "#f6ff00" },
{ "lat": 46.811000, "lng": 1.692390, "grv": "#f6ff00" },
{ "lat": 46.801800, "lng": 1.696760, "grv": "#f6ff00" },
{ "lat": 46.804400, "lng": 1.698930, "grv": "#f6ff00" },
{ "lat": 46.816700, "lng": 1.723670, "grv": "#f6ff00" },
{ "lat": 46.779500, "lng": 1.707200, "grv": "#f6ff00" },
{ "lat": 46.819000, "lng": 1.684620, "grv": "#f6ff00" },
{ "lat": 46.802200, "lng": 1.632290, "grv": "#f6ff00" },
{ "lat": 46.817700, "lng": 1.697070, "grv": "#f6ff00" },
{ "lat": 46.803200, "lng": 1.652040, "grv": "#f6ff00" },
{ "lat": 46.805800, "lng": 1.716760, "grv": "#f6ff00" },
{ "lat": 46.833500, "lng": 1.720710, "grv": "#f6ff00" },
{ "lat": 46.800500, "lng": 1.716530, "grv": "#f6ff00" },
{ "lat": 46.794900, "lng": 1.692020, "grv": "#f6ff00" },
{ "lat": 46.797100, "lng": 1.717440, "grv": "#f6ff00" },
{ "lat": 46.657200, "lng": 1.749540, "grv": "#f6ff00" },
{ "lat": 46.817200, "lng": 1.698600, "grv": "#f6ff00" },
{ "lat": 46.762200, "lng": 1.678470, "grv": "#f6ff00" },
{ "lat": 46.578100, "lng": 1.512480, "grv": "#f6ff00" },
{ "lat": 46.803400, "lng": 1.716150, "grv": "#f6ff00" },
{ "lat": 46.806500, "lng": 1.675670, "grv": "#f6ff00" },
{ "lat": 46.788700, "lng": 1.691310, "grv": "#f6ff00" },
{ "lat": 46.819200, "lng": 1.697300, "grv": "#f6ff00" },
{ "lat": 46.631300, "lng": 1.130710, "grv": "#f6ff00" },
{ "lat": 46.886000, "lng": 1.938560, "grv": "#f6ff00" },
{ "lat": 46.811200, "lng": 1.683620, "grv": "#f6ff00" },
{ "lat": 46.809500, "lng": 1.703250, "grv": "#f6ff00" },
{ "lat": 46.820100, "lng": 1.702810, "grv": "#f6ff00" },
{ "lat": 46.733100, "lng": 1.557980, "grv": "#f6ff00" },
{ "lat": 46.762600, "lng": 1.700830, "grv": "#f6ff00" },
{ "lat": 46.795900, "lng": 1.697450, "grv": "#f6ff00" },
{ "lat": 46.810500, "lng": 1.686190, "grv": "#f6ff00" },
{ "lat": 46.788700, "lng": 1.691310, "grv": "#f6ff00" },
{ "lat": 46.815200, "lng": 1.708480, "grv": "#f6ff00" },
{ "lat": 46.574200, "lng": 1.982260, "grv": "#f6ff00" },
{ "lat": 46.809600, "lng": 1.684470, "grv": "#f6ff00" },
{ "lat": 46.801600, "lng": 1.685960, "grv": "#f6ff00" },
{ "lat": 46.804300, "lng": 1.692170, "grv": "#f6ff00" },
{ "lat": 46.806600, "lng": 1.680950, "grv": "#f6ff00" },
{ "lat": 46.825400, "lng": 1.700200, "grv": "#f6ff00" },
{ "lat": 46.792370, "lng": 1.735480, "grv": "#f6ff00" },
{ "lat": 46.807300, "lng": 1.686570, "grv": "#f6ff00" },
{ "lat": 46.809400, "lng": 1.697700, "grv": "#f6ff00" },
{ "lat": 46.818500, "lng": 1.684600, "grv": "#f6ff00" },
{ "lat": 46.798100, "lng": 1.638640, "grv": "#f6ff00" },
{ "lat": 46.801200, "lng": 1.702960, "grv": "#f6ff00" },
{ "lat": 46.820500, "lng": 1.726050, "grv": "#f6ff00" },
{ "lat": 46.788000, "lng": 1.703690, "grv": "#f6ff00" },
{ "lat": 46.948890, "lng": 1.996920, "grv": "#f6ff00" },
{ "lat": 46.829200, "lng": 1.710130, "grv": "#f6ff00" },
{ "lat": 46.808900, "lng": 1.690410, "grv": "#f6ff00" },
{ "lat": 46.809500, "lng": 1.697790, "grv": "#f6ff00" },
{ "lat": 46.812600, "lng": 1.688900, "grv": "#f6ff00" },
{ "lat": 46.851900, "lng": 1.701250, "grv": "#f6ff00" },
{ "lat": 46.778600, "lng": 1.707370, "grv": "#f6ff00" },
{ "lat": 46.811200, "lng": 1.688460, "grv": "#f6ff00" },
{ "lat": 46.799300, "lng": 1.714560, "grv": "#f6ff00" },
{ "lat": 46.804400, "lng": 1.691890, "grv": "#f6ff00" },
{ "lat": 46.811200, "lng": 1.682640, "grv": "#f6ff00" },
{ "lat": 46.809500, "lng": 1.703290, "grv": "#f6ff00" },
{ "lat": 46.786000, "lng": 1.679040, "grv": "#f6ff00" },
{ "lat": 46.812100, "lng": 1.721640, "grv": "#f6ff00" },
{ "lat": 46.813000, "lng": 1.688620, "grv": "#f6ff00" },
{ "lat": 46.805200, "lng": 1.698530, "grv": "#f6ff00" },
{ "lat": 46.758900, "lng": 1.721150, "grv": "#f6ff00" },
{ "lat": 46.676800, "lng": 1.496200, "grv": "#f6ff00" },
{ "lat": 46.638200, "lng": 1.061780, "grv": "#f6ff00" },
{ "lat": 46.819500, "lng": 1.697140, "grv": "#f6ff00" },
{ "lat": 46.795900, "lng": 1.695960, "grv": "#f6ff00" },
{ "lat": 46.804000, "lng": 1.714930, "grv": "#f6ff00" },
{ "lat": 46.763080, "lng": 1.808470, "grv": "#f6ff00" },
{ "lat": 46.815400, "lng": 1.696660, "grv": "#f6ff00" },
{ "lat": 46.809000, "lng": 1.689960, "grv": "#f6ff00" },
{ "lat": 46.799700, "lng": 1.699300, "grv": "#f6ff00" },
{ "lat": 46.814800, "lng": 1.696780, "grv": "#f6ff00" },
{ "lat": 46.790900, "lng": 1.706160, "grv": "#f6ff00" },
{ "lat": 46.808500, "lng": 1.676610, "grv": "#f6ff00" },
{ "lat": 46.738600, "lng": 1.727500, "grv": "#f6ff00" },
{ "lat": 46.707400, "lng": 1.668520, "grv": "#f6ff00" },
{ "lat": 46.603600, "lng": 1.629920, "grv": "#f6ff00" },
{ "lat": 46.826900, "lng": 1.704540, "grv": "#f6ff00" },
{ "lat": 46.845500, "lng": 1.708720, "grv": "#f6ff00" },
{ "lat": 46.802900, "lng": 1.705170, "grv": "#f6ff00" },
{ "lat": 46.836000, "lng": 1.704610, "grv": "#f6ff00" },
{ "lat": 46.810400, "lng": 1.705630, "grv": "#f6ff00" },
{ "lat": 46.810500, "lng": 1.687500, "grv": "#f6ff00" },
{ "lat": 46.758900, "lng": 1.721150, "grv": "#f6ff00" },
{ "lat": 46.804200, "lng": 1.691820, "grv": "#f6ff00" },
{ "lat": 46.800300, "lng": 1.713860, "grv": "#f6ff00" },
{ "lat": 46.811600, "lng": 1.722170, "grv": "#f6ff00" },
{ "lat": 46.808500, "lng": 1.714960, "grv": "#f6ff00" },
{ "lat": 46.845500, "lng": 1.708760, "grv": "#f6ff00" },
{ "lat": 46.809600, "lng": 1.684190, "grv": "#f6ff00" },
{ "lat": 46.811300, "lng": 1.683850, "grv": "#f6ff00" },
{ "lat": 46.454600, "lng": 1.666250, "grv": "#f6ff00" },
{ "lat": 46.463400, "lng": 1.823710, "grv": "#f6ff00" },
{ "lat": 46.795400, "lng": 1.665190, "grv": "#f6ff00" },
{ "lat": 46.809900, "lng": 1.702810, "grv": "#f6ff00" },
{ "lat": 46.827800, "lng": 1.632290, "grv": "#f6ff00" },
{ "lat": 46.849900, "lng": 1.710950, "grv": "#f6ff00" },
{ "lat": 46.702700, "lng": 1.038480, "grv": "#f6ff00" },
{ "lat": 46.799200, "lng": 1.697820, "grv": "#f6ff00" },
{ "lat": 46.786500, "lng": 1.677330, "grv": "#f6ff00" },
{ "lat": 46.603300, "lng": 1.305300, "grv": "#f6ff00" },
{ "lat": 46.648100, "lng": 1.950000, "grv": "#f6ff00" },
{ "lat": 46.795900, "lng": 1.694770, "grv": "#f6ff00" },
{ "lat": 46.812600, "lng": 1.696960, "grv": "#f6ff00" },
{ "lat": 46.764100, "lng": 1.718420, "grv": "#f6ff00" },
{ "lat": 46.796300, "lng": 1.676480, "grv": "#f6ff00" },
{ "lat": 46.820400, "lng": 1.736020, "grv": "#f6ff00" },
{ "lat": 46.809200, "lng": 1.689750, "grv": "#f6ff00" },
{ "lat": 46.788700, "lng": 1.659870, "grv": "#f6ff00" },
{ "lat": 46.789700, "lng": 1.721790, "grv": "#f6ff00" },
{ "lat": 46.810000, "lng": 1.687380, "grv": "#f6ff00" },
{ "lat": 46.818900, "lng": 1.721540, "grv": "#f6ff00" },
{ "lat": 46.812400, "lng": 1.715960, "grv": "#f6ff00" },
{ "lat": 46.793800, "lng": 1.736050, "grv": "#f6ff00" },
{ "lat": 46.803100, "lng": 1.706410, "grv": "#f6ff00" },
{ "lat": 46.815900, "lng": 1.684670, "grv": "#f6ff00" },
{ "lat": 46.798000, "lng": 1.638510, "grv": "#f6ff00" },
{ "lat": 46.812600, "lng": 1.696960, "grv": "#f6ff00" },
{ "lat": 46.805800, "lng": 1.694210, "grv": "#f6ff00" },
{ "lat": 46.809000, "lng": 1.690230, "grv": "#f6ff00" },
{ "lat": 46.798700, "lng": 1.698080, "grv": "#f6ff00" },
{ "lat": 46.788900, "lng": 1.702660, "grv": "#f6ff00" },
{ "lat": 46.788000, "lng": 1.672780, "grv": "#f6ff00" },
{ "lat": 46.808900, "lng": 1.691790, "grv": "#f6ff00" },
{ "lat": 46.900600, "lng": 1.369360, "grv": "#f6ff00" },
{ "lat": 46.804400, "lng": 1.681570, "grv": "#f6ff00" },
{ "lat": 46.832000, "lng": 1.702850, "grv": "#f6ff00" },
{ "lat": 46.788000, "lng": 1.703530, "grv": "#f6ff00" },
{ "lat": 46.814200, "lng": 1.696640, "grv": "#f6ff00" },
{ "lat": 46.825900, "lng": 1.700120, "grv": "#f6ff00" },
{ "lat": 46.778200, "lng": 1.646610, "grv": "#f6ff00" },
{ "lat": 46.804200, "lng": 1.700980, "grv": "#f6ff00" },
{ "lat": 46.793100, "lng": 1.711180, "grv": "#f6ff00" },
{ "lat": 46.778500, "lng": 1.650870, "grv": "#f6ff00" },
{ "lat": 46.788700, "lng": 1.691310, "grv": "#f6ff00" },
{ "lat": 46.810200, "lng": 1.687300, "grv": "#f6ff00" },
{ "lat": 46.822000, "lng": 1.699220, "grv": "#f6ff00" },
{ "lat": 46.808400, "lng": 1.671410, "grv": "#f6ff00" },
{ "lat": 46.813200, "lng": 1.632450, "grv": "#f6ff00" },
{ "lat": 46.807100, "lng": 1.686540, "grv": "#f6ff00" },
{ "lat": 46.793200, "lng": 1.711320, "grv": "#f6ff00" },
{ "lat": 46.778300, "lng": 1.646780, "grv": "#f6ff00" },
{ "lat": 46.812300, "lng": 1.697870, "grv": "#f6ff00" },
{ "lat": 46.806900, "lng": 1.696110, "grv": "#f6ff00" },
{ "lat": 46.799300, "lng": 1.632340, "grv": "#f6ff00" },
{ "lat": 46.816900, "lng": 1.696950, "grv": "#f6ff00" },
{ "lat": 46.804200, "lng": 1.691740, "grv": "#f6ff00" },
{ "lat": 46.812700, "lng": 1.692250, "grv": "#f6ff00" },
{ "lat": 46.838300, "lng": 1.705660, "grv": "#f6ff00" },
{ "lat": 46.821400, "lng": 1.697500, "grv": "#f6ff00" },
{ "lat": 46.788700, "lng": 1.691310, "grv": "#f6ff00" },
{ "lat": 46.811200, "lng": 1.689740, "grv": "#f6ff00" },
{ "lat": 46.817200, "lng": 1.684650, "grv": "#f6ff00" },
{ "lat": 46.813000, "lng": 1.688710, "grv": "#f6ff00" },
{ "lat": 46.802900, "lng": 1.719390, "grv": "#f6ff00" },
{ "lat": 46.784200, "lng": 1.655830, "grv": "#f6ff00" },
{ "lat": 46.802800, "lng": 1.703940, "grv": "#f6ff00" },
{ "lat": 46.982900, "lng": 1.175810, "grv": "#f6ff00" },
{ "lat": 46.818500, "lng": 1.706730, "grv": "#f6ff00" },
{ "lat": 46.804200, "lng": 1.691720, "grv": "#f6ff00" },
{ "lat": 46.818100, "lng": 1.696890, "grv": "#f6ff00" },
{ "lat": 46.798900, "lng": 1.692340, "grv": "#f6ff00" },
{ "lat": 46.805400, "lng": 1.722360, "grv": "#f6ff00" },
{ "lat": 46.811700, "lng": 1.695930, "grv": "#f6ff00" },
{ "lat": 46.813300, "lng": 1.696820, "grv": "#f6ff00" },
{ "lat": 46.788700, "lng": 1.747100, "grv": "#f6ff00" },
{ "lat": 46.799000, "lng": 1.697960, "grv": "#f6ff00" },
{ "lat": 46.821000, "lng": 1.718930, "grv": "#f6ff00" },
{ "lat": 46.811200, "lng": 1.682730, "grv": "#f6ff00" },
{ "lat": 46.815100, "lng": 1.708260, "grv": "#f6ff00" },
{ "lat": 46.820300, "lng": 1.697260, "grv": "#f6ff00" },
{ "lat": 46.787000, "lng": 1.750010, "grv": "#f6ff00" },
{ "lat": 46.816400, "lng": 1.696870, "grv": "#f6ff00" },
{ "lat": 46.575000, "lng": 1.874100, "grv": "#f6ff00" },
{ "lat": 46.807700, "lng": 1.690790, "grv": "#f6ff00" },
{ "lat": 46.805400, "lng": 1.711810, "grv": "#f6ff00" },
{ "lat": 46.800400, "lng": 1.710200, "grv": "#f6ff00" },
{ "lat": 46.810500, "lng": 1.700340, "grv": "#f6ff00" },
{ "lat": 46.989300, "lng": 1.388220, "grv": "#f6ff00" },
{ "lat": 46.793700, "lng": 1.717800, "grv": "#f6ff00" },
{ "lat": 46.802000, "lng": 1.713570, "grv": "#f6ff00" },
{ "lat": 46.808600, "lng": 1.705130, "grv": "#f6ff00" },
{ "lat": 46.772100, "lng": 1.655630, "grv": "#f6ff00" },
{ "lat": 46.831600, "lng": 1.715610, "grv": "#f6ff00" },
{ "lat": 46.820000, "lng": 1.670240, "grv": "#f6ff00" },
{ "lat": 46.807600, "lng": 1.680760, "grv": "#f6ff00" },
{ "lat": 46.801600, "lng": 1.686020, "grv": "#f6ff00" },
{ "lat": 46.820400, "lng": 1.736020, "grv": "#f6ff00" },
{ "lat": 46.788000, "lng": 1.703690, "grv": "#f6ff00" },
{ "lat": 46.771800, "lng": 1.657450, "grv": "#f6ff00" },
{ "lat": 46.819800, "lng": 1.685240, "grv": "#f6ff00" },
{ "lat": 46.820000, "lng": 1.684510, "grv": "#f6ff00" },
{ "lat": 46.796200, "lng": 1.715910, "grv": "#f6ff00" },
{ "lat": 46.799500, "lng": 1.714430, "grv": "#f6ff00" },
{ "lat": 46.842300, "lng": 1.673280, "grv": "#f6ff00" },
{ "lat": 46.791700, "lng": 1.712040, "grv": "#f6ff00" },
{ "lat": 46.805500, "lng": 1.711860, "grv": "#f6ff00" },
{ "lat": 46.557000, "lng": 1.975120, "grv": "#f6ff00" },
{ "lat": 46.800000, "lng": 1.690110, "grv": "#f6ff00" },
{ "lat": 46.765800, "lng": 1.717270, "grv": "#f6ff00" },
{ "lat": 46.810000, "lng": 1.702350, "grv": "#f6ff00" },
{ "lat": 46.354000, "lng": 1.391000, "grv": "#f6ff00" },
{ "lat": 46.319000, "lng": 1.419000, "grv": "#f6ff00" },
{ "lat": 46.130000, "lng": 1.350000, "grv": "#f6ff00" },
{ "lat": 46.197000, "lng": 1.122000, "grv": "#f6ff00" },
{ "lat": 46.072000, "lng": 1.280000, "grv": "#f6ff00" },
{ "lat": 46.309000, "lng": 1.290000, "grv": "#f6ff00" },
{ "lat": 46.199000, "lng": 1.297000, "grv": "#f6ff00" },
{ "lat": 46.135700, "lng": 1.311190, "grv": "#f6ff00" },
{ "lat": 46.200700, "lng": 1.323480, "grv": "#f6ff00" },
{ "lat": 46.139000, "lng": 1.443430, "grv": "#f6ff00" },
{ "lat": 46.002000, "lng": 1.163990, "grv": "#f6ff00" },
{ "lat": 46.097000, "lng": 1.603000, "grv": "#f6ff00" },
{ "lat": 46.054000, "lng": 1.735000, "grv": "#f6ff00" },
{ "lat": 46.240000, "lng": 1.490000, "grv": "#f6ff00" },
{ "lat": 46.250000, "lng": 1.490000, "grv": "#f6ff00" },
{ "lat": 46.240000, "lng": 1.480000, "grv": "#f6ff00" },
{ "lat": 46.119000, "lng": 1.630000, "grv": "#f6ff00" },
{ "lat": 46.537000, "lng": 1.252000, "grv": "#f6ff00" },
{ "lat": 46.885000, "lng": 1.451000, "grv": "#f6ff00" },
{ "lat": 46.693000, "lng": 1.537000, "grv": "#f6ff00" },
{ "lat": 46.780000, "lng": 1.770000, "grv": "#f6ff00" },
{ "lat": 46.895000, "lng": 1.854000, "grv": "#f6ff00" },
{ "lat": 46.728000, "lng": 1.670000, "grv": "#f6ff00" },
{ "lat": 46.825000, "lng": 1.230000, "grv": "#f6ff00" },
{ "lat": 46.635000, "lng": 1.176000, "grv": "#f6ff00" },
{ "lat": 46.882000, "lng": 1.414000, "grv": "#f6ff00" },
{ "lat": 46.935000, "lng": 1.634000, "grv": "#f6ff00" },
{ "lat": 46.780000, "lng": 1.330000, "grv": "#f6ff00" },
{ "lat": 46.439000, "lng": 1.722000, "grv": "#f6ff00" },
{ "lat": 46.592000, "lng": 1.497000, "grv": "#f6ff00" },
{ "lat": 46.638000, "lng": 1.065000, "grv": "#f6ff00" },
{ "lat": 46.845000, "lng": 1.532000, "grv": "#f6ff00" },
{ "lat": 46.438000, "lng": 1.826000, "grv": "#f6ff00" },
{ "lat": 46.864000, "lng": 1.063000, "grv": "#f6ff00" },
{ "lat": 46.596000, "lng": 1.520000, "grv": "#f6ff00" },
{ "lat": 46.810700, "lng": 1.705810, "grv": "#f6ff00" },
{ "lat": 46.772900, "lng": 1.735310, "grv": "#f6ff00" },
{ "lat": 46.804000, "lng": 1.701140, "grv": "#f6ff00" },
{ "lat": 46.809900, "lng": 1.702670, "grv": "#f6ff00" },
{ "lat": 46.804800, "lng": 1.744250, "grv": "#f6ff00" },
{ "lat": 46.762100, "lng": 1.635340, "grv": "#f6ff00" },
{ "lat": 46.810500, "lng": 1.705760, "grv": "#f6ff00" },
{ "lat": 46.801500, "lng": 1.707230, "grv": "#f6ff00" },
{ "lat": 46.809500, "lng": 1.155720, "grv": "#f6ff00" },
{ "lat": 46.804100, "lng": 1.714620, "grv": "#f6ff00" },
{ "lat": 46.694100, "lng": 1.795210, "grv": "#f6ff00" },
{ "lat": 46.781700, "lng": 1.706660, "grv": "#f6ff00" },
{ "lat": 46.821000, "lng": 1.717480, "grv": "#f6ff00" },
{ "lat": 46.766700, "lng": 1.716420, "grv": "#f6ff00" },
{ "lat": 46.813100, "lng": 1.725430, "grv": "#f6ff00" },
{ "lat": 46.935800, "lng": 1.888610, "grv": "#f6ff00" },
{ "lat": 46.802800, "lng": 1.704030, "grv": "#f6ff00" },
{ "lat": 46.808600, "lng": 1.704630, "grv": "#f6ff00" },
{ "lat": 46.547500, "lng": 1.932750, "grv": "#f6ff00" },
{ "lat": 46.825800, "lng": 1.700580, "grv": "#f6ff00" },
{ "lat": 46.801400, "lng": 1.738370, "grv": "#f6ff00" },
{ "lat": 46.971800, "lng": 1.589620, "grv": "#f6ff00" },
{ "lat": 46.806400, "lng": 1.731710, "grv": "#f6ff00" },
{ "lat": 46.788820, "lng": 1.691510, "grv": "#f6ff00" },
{ "lat": 46.803400, "lng": 1.707840, "grv": "#f6ff00" },
{ "lat": 46.580800, "lng": 1.598340, "grv": "#f6ff00" },
{ "lat": 46.818900, "lng": 1.687110, "grv": "#f6ff00" },
{ "lat": 46.788700, "lng": 1.691310, "grv": "#f6ff00" },
{ "lat": 46.543500, "lng": 1.392280, "grv": "#f6ff00" },
{ "lat": 46.793800, "lng": 1.734080, "grv": "#f6ff00" },
{ "lat": 46.929200, "lng": 1.239210, "grv": "#f6ff00" },
{ "lat": 46.797400, "lng": 1.667590, "grv": "#f6ff00" },
{ "lat": 46.785200, "lng": 1.656690, "grv": "#f6ff00" },
{ "lat": 46.595200, "lng": 1.056990, "grv": "#f6ff00" },
{ "lat": 46.771400, "lng": 1.661670, "grv": "#f6ff00" },
{ "lat": 46.789700, "lng": 1.691260, "grv": "#f6ff00" },
{ "lat": 46.605900, "lng": 1.502410, "grv": "#f6ff00" },
{ "lat": 46.826600, "lng": 1.638450, "grv": "#f6ff00" },
{ "lat": 46.106000, "lng": 1.319000, "grv": "#f6ff00" },
{ "lat": 46.004000, "lng": 1.468000, "grv": "#f6ff00" },
{ "lat": 46.797000, "lng": 1.488000, "grv": "#ffae00" },
{ "lat": 46.896000, "lng": 1.422000, "grv": "#ffae00" },
{ "lat": 46.636000, "lng": 1.082000, "grv": "#ffae00" },
{ "lat": 46.871100, "lng": 1.660870, "grv": "#ffae00" },
{ "lat": 46.822800, "lng": 1.656460, "grv": "#ffae00" },
{ "lat": 46.602900, "lng": 1.809770, "grv": "#ffae00" },
{ "lat": 46.823000, "lng": 1.697700, "grv": "#ffae00" },
{ "lat": 46.796300, "lng": 1.699070, "grv": "#ffae00" },
{ "lat": 46.793100, "lng": 1.711340, "grv": "#ffae00" },
{ "lat": 46.915300, "lng": 1.482740, "grv": "#ffae00" },
{ "lat": 46.807700, "lng": 1.683610, "grv": "#ffae00" },
{ "lat": 46.788800, "lng": 1.663380, "grv": "#ffae00" },
{ "lat": 46.572300, "lng": 1.975870, "grv": "#ffae00" },
{ "lat": 46.703900, "lng": 1.878600, "grv": "#ffae00" },
{ "lat": 46.817900, "lng": 1.691930, "grv": "#ffae00" },
{ "lat": 46.780400, "lng": 1.652560, "grv": "#ffae00" },
{ "lat": 46.589000, "lng": 1.995000, "grv": "#ffae00" },
{ "lat": 46.907000, "lng": 1.459000, "grv": "#ffae00" },
{ "lat": 46.835000, "lng": 1.863000, "grv": "#ffae00" },
{ "lat": 46.933000, "lng": 1.342000, "grv": "#ffae00" },
{ "lat": 46.814000, "lng": 1.955000, "grv": "#ffae00" },
{ "lat": 46.810100, "lng": 1.687960, "grv": "#ffae00" },
{ "lat": 46.751100, "lng": 1.566750, "grv": "#ffae00" },
{ "lat": 46.183500, "lng": 1.218580, "grv": "#ffae00" },
{ "lat": 46.994000, "lng": 1.170000, "grv": "#ffae00" },
{ "lat": 46.182000, "lng": 1.897000, "grv": "#ffae00" },
{ "lat": 46.144000, "lng": 1.923000, "grv": "#ffae00" },
{ "lat": 46.244000, "lng": 1.487000, "grv": "#ffae00" },
{ "lat": 46.227000, "lng": 1.716000, "grv": "#ffae00" },
{ "lat": 46.238000, "lng": 1.911000, "grv": "#ffae00" },
{ "lat": 46.363000, "lng": 1.835000, "grv": "#ffae00" },
{ "lat": 46.166000, "lng": 1.607000, "grv": "#ffae00" },
{ "lat": 46.224000, "lng": 1.704000, "grv": "#ffae00" },
{ "lat": 46.245000, "lng": 1.902000, "grv": "#ffae00" },
{ "lat": 46.229000, "lng": 1.686000, "grv": "#ffae00" },
{ "lat": 46.125000, "lng": 1.967000, "grv": "#ffae00" },
{ "lat": 46.192000, "lng": 1.837000, "grv": "#ffae00" },
{ "lat": 46.184000, "lng": 1.911000, "grv": "#ffae00" },
{ "lat": 46.200000, "lng": 1.490000, "grv": "#ffae00" },
{ "lat": 46.190000, "lng": 1.826000, "grv": "#ffae00" },
{ "lat": 46.080000, "lng": 1.580000, "grv": "#ffae00" },
{ "lat": 46.186000, "lng": 1.660000, "grv": "#ffae00" },
{ "lat": 46.240000, "lng": 1.530000, "grv": "#ffae00" },
{ "lat": 46.133000, "lng": 1.821000, "grv": "#ffae00" },
{ "lat": 46.203000, "lng": 1.855000, "grv": "#ffae00" },
{ "lat": 46.090000, "lng": 1.569000, "grv": "#ffae00" },
{ "lat": 46.211000, "lng": 1.997000, "grv": "#ffae00" },
{ "lat": 46.122000, "lng": 1.625000, "grv": "#ffae00" },
{ "lat": 46.244000, "lng": 1.485000, "grv": "#ffae00" },
{ "lat": 46.144000, "lng": 1.911000, "grv": "#ffae00" },
{ "lat": 46.172000, "lng": 1.795000, "grv": "#ffae00" },
{ "lat": 46.224000, "lng": 1.574000, "grv": "#ffae00" },
{ "lat": 46.201000, "lng": 1.832000, "grv": "#ffae00" },
{ "lat": 46.160000, "lng": 1.538000, "grv": "#ffae00" },
{ "lat": 46.177000, "lng": 1.902000, "grv": "#ffae00" },
{ "lat": 46.264000, "lng": 1.940000, "grv": "#ffae00" },
{ "lat": 46.328000, "lng": 1.903000, "grv": "#ffae00" },
{ "lat": 46.203000, "lng": 1.759000, "grv": "#ffae00" },
{ "lat": 46.410000, "lng": 1.812000, "grv": "#ffae00" },
{ "lat": 46.178000, "lng": 1.833000, "grv": "#ffae00" },
{ "lat": 46.240000, "lng": 1.561000, "grv": "#ffae00" },
{ "lat": 46.090000, "lng": 1.864000, "grv": "#ffae00" },
{ "lat": 46.219000, "lng": 1.727000, "grv": "#ffae00" },
{ "lat": 46.208000, "lng": 1.980000, "grv": "#ffae00" },
{ "lat": 46.133000, "lng": 1.937000, "grv": "#ffae00" },
{ "lat": 46.172000, "lng": 1.960000, "grv": "#ffae00" },
{ "lat": 46.260000, "lng": 1.910000, "grv": "#ffae00" },
{ "lat": 46.310000, "lng": 1.975000, "grv": "#ffae00" },
{ "lat": 46.335000, "lng": 1.849000, "grv": "#ffae00" },
{ "lat": 46.177000, "lng": 1.933000, "grv": "#ffae00" },
{ "lat": 46.251000, "lng": 1.466000, "grv": "#ffae00" },
{ "lat": 46.097000, "lng": 1.670000, "grv": "#ffae00" },
{ "lat": 46.432000, "lng": 1.959000, "grv": "#ffae00" },
{ "lat": 46.180000, "lng": 1.740000, "grv": "#ffae00" },
{ "lat": 46.217000, "lng": 1.983000, "grv": "#ffae00" },
{ "lat": 46.094000, "lng": 1.983000, "grv": "#ffae00" },
{ "lat": 46.243000, "lng": 1.539000, "grv": "#ffae00" },
{ "lat": 46.143000, "lng": 1.914000, "grv": "#ffae00" },
{ "lat": 46.185000, "lng": 1.917000, "grv": "#ffae00" },
{ "lat": 46.305000, "lng": 1.771000, "grv": "#ffae00" },
{ "lat": 46.237000, "lng": 1.853000, "grv": "#ffae00" },
{ "lat": 46.195000, "lng": 1.782000, "grv": "#ffae00" },
{ "lat": 46.250000, "lng": 1.499000, "grv": "#ffae00" },
{ "lat": 46.120000, "lng": 1.661000, "grv": "#ffae00" },
{ "lat": 46.385000, "lng": 1.872000, "grv": "#ffae00" },
{ "lat": 46.310000, "lng": 1.666000, "grv": "#ffae00" },
{ "lat": 46.295000, "lng": 1.676000, "grv": "#ffae00" },
{ "lat": 46.424000, "lng": 1.906000, "grv": "#ffae00" },
{ "lat": 46.244000, "lng": 1.874000, "grv": "#ffae00" },
{ "lat": 46.308000, "lng": 1.669000, "grv": "#ffae00" },
{ "lat": 46.167000, "lng": 1.132000, "grv": "#ffae00" },
{ "lat": 46.111000, "lng": 1.986000, "grv": "#ffae00" },
{ "lat": 46.417000, "lng": 1.845000, "grv": "#ffae00" },
{ "lat": 46.200000, "lng": 1.490000, "grv": "#ffae00" },
{ "lat": 46.183000, "lng": 1.906000, "grv": "#ffae00" },
{ "lat": 46.261000, "lng": 1.920000, "grv": "#ffae00" },
{ "lat": 46.240000, "lng": 1.541000, "grv": "#ffae00" },
{ "lat": 46.209000, "lng": 1.764000, "grv": "#ffae00" },
{ "lat": 46.406000, "lng": 1.594000, "grv": "#ffae00" },
{ "lat": 46.225000, "lng": 1.393000, "grv": "#ffae00" },
{ "lat": 46.186000, "lng": 1.912000, "grv": "#ffae00" },
{ "lat": 46.144000, "lng": 1.911000, "grv": "#ffae00" },
{ "lat": 46.343000, "lng": 1.653000, "grv": "#ffae00" },
{ "lat": 46.161000, "lng": 1.537000, "grv": "#ffae00" },
{ "lat": 46.193000, "lng": 1.837000, "grv": "#ffae00" },
{ "lat": 46.112000, "lng": 1.611000, "grv": "#ffae00" },
{ "lat": 46.620000, "lng": 1.160000, "grv": "#ffae00" },
{ "lat": 46.631000, "lng": 1.083000, "grv": "#ffae00" },
{ "lat": 46.634000, "lng": 1.068000, "grv": "#ffae00" },
{ "lat": 46.590000, "lng": 1.510000, "grv": "#ffae00" },
{ "lat": 46.642000, "lng": 1.063000, "grv": "#ffae00" },
{ "lat": 46.604000, "lng": 1.869000, "grv": "#ffae00" },
{ "lat": 46.635000, "lng": 1.058000, "grv": "#ffae00" },
{ "lat": 46.572000, "lng": 1.468000, "grv": "#ffae00" },
{ "lat": 46.894000, "lng": 1.430000, "grv": "#ffae00" },
{ "lat": 46.936000, "lng": 1.386000, "grv": "#ffae00" },
{ "lat": 46.992000, "lng": 1.179000, "grv": "#ffae00" },
{ "lat": 46.849000, "lng": 1.539000, "grv": "#ffae00" },
{ "lat": 46.643000, "lng": 1.058000, "grv": "#ffae00" },
{ "lat": 46.550000, "lng": 1.750000, "grv": "#ffae00" },
{ "lat": 46.379000, "lng": 1.226000, "grv": "#ffae00" },
{ "lat": 46.985000, "lng": 1.179000, "grv": "#ffae00" },
{ "lat": 46.986000, "lng": 1.413000, "grv": "#ffae00" },
{ "lat": 46.518000, "lng": 1.504000, "grv": "#ffae00" },
{ "lat": 46.553000, "lng": 1.554000, "grv": "#ffae00" },
{ "lat": 46.440000, "lng": 1.480000, "grv": "#ffae00" },
{ "lat": 46.940000, "lng": 1.320000, "grv": "#ffae00" },
{ "lat": 46.635000, "lng": 1.191000, "grv": "#ffae00" },
{ "lat": 46.637000, "lng": 1.071000, "grv": "#ffae00" },
{ "lat": 46.540000, "lng": 1.630000, "grv": "#ffae00" },
{ "lat": 46.470000, "lng": 1.530000, "grv": "#ffae00" },
{ "lat": 46.904000, "lng": 1.867000, "grv": "#ffae00" },
{ "lat": 46.849000, "lng": 1.748000, "grv": "#ffae00" },
{ "lat": 46.641000, "lng": 1.018000, "grv": "#ffae00" },
{ "lat": 46.781000, "lng": 1.650000, "grv": "#ffae00" },
{ "lat": 46.374000, "lng": 1.440000, "grv": "#ffae00" },
{ "lat": 46.679000, "lng": 1.700000, "grv": "#ffae00" },
{ "lat": 46.635000, "lng": 1.058000, "grv": "#ffae00" },
{ "lat": 46.586000, "lng": 1.988000, "grv": "#ffae00" },
{ "lat": 46.422000, "lng": 1.470000, "grv": "#ffae00" },
{ "lat": 46.758000, "lng": 1.867000, "grv": "#ffae00" },
{ "lat": 46.741000, "lng": 1.409000, "grv": "#ffae00" },
{ "lat": 46.895000, "lng": 1.474000, "grv": "#ffae00" },
{ "lat": 46.628000, "lng": 1.140000, "grv": "#ffae00" },
{ "lat": 46.635000, "lng": 1.080000, "grv": "#ffae00" },
{ "lat": 46.430000, "lng": 1.840000, "grv": "#ffae00" },
{ "lat": 46.612000, "lng": 1.288000, "grv": "#ffae00" },
{ "lat": 46.619000, "lng": 1.534000, "grv": "#ffae00" },
{ "lat": 46.748000, "lng": 1.832000, "grv": "#ffae00" },
{ "lat": 46.997000, "lng": 1.367000, "grv": "#ffae00" },
{ "lat": 46.629000, "lng": 1.042000, "grv": "#ffae00" },
{ "lat": 46.676000, "lng": 1.792000, "grv": "#ffae00" },
{ "lat": 46.747000, "lng": 1.832000, "grv": "#ffae00" },
{ "lat": 46.400000, "lng": 1.460000, "grv": "#ffae00" },
{ "lat": 46.587000, "lng": 1.513000, "grv": "#ffae00" },
{ "lat": 46.946000, "lng": 1.440000, "grv": "#ffae00" },
{ "lat": 46.484000, "lng": 1.687000, "grv": "#ffae00" },
{ "lat": 46.831000, "lng": 1.836000, "grv": "#ffae00" },
{ "lat": 46.637000, "lng": 1.062000, "grv": "#ffae00" },
{ "lat": 46.600000, "lng": 1.999000, "grv": "#ffae00" },
{ "lat": 46.517000, "lng": 1.500000, "grv": "#ffae00" },
{ "lat": 46.824000, "lng": 1.208000, "grv": "#ffae00" },
{ "lat": 46.989000, "lng": 1.607000, "grv": "#ffae00" },
{ "lat": 46.826000, "lng": 1.234000, "grv": "#ffae00" },
{ "lat": 46.523000, "lng": 1.496000, "grv": "#ffae00" },
{ "lat": 46.632000, "lng": 1.482000, "grv": "#ffae00" },
{ "lat": 46.500000, "lng": 1.449000, "grv": "#ffae00" },
{ "lat": 46.593000, "lng": 1.524000, "grv": "#ffae00" },
{ "lat": 46.392000, "lng": 1.447000, "grv": "#ffae00" },
{ "lat": 46.896000, "lng": 1.430000, "grv": "#ffae00" },
{ "lat": 46.535000, "lng": 1.694000, "grv": "#ffae00" },
{ "lat": 46.899000, "lng": 1.643000, "grv": "#ffae00" },
{ "lat": 46.481000, "lng": 1.774000, "grv": "#ffae00" },
{ "lat": 46.951000, "lng": 1.995000, "grv": "#ffae00" },
{ "lat": 46.855000, "lng": 1.136000, "grv": "#ffae00" },
{ "lat": 46.593000, "lng": 1.997000, "grv": "#ffae00" },
{ "lat": 46.865000, "lng": 1.710000, "grv": "#ffae00" },
{ "lat": 46.827000, "lng": 1.384000, "grv": "#ffae00" },
{ "lat": 46.616000, "lng": 1.128000, "grv": "#ffae00" },
{ "lat": 46.633000, "lng": 1.057000, "grv": "#ffae00" },
{ "lat": 46.633000, "lng": 1.056000, "grv": "#ffae00" },
{ "lat": 46.580000, "lng": 1.092000, "grv": "#ffae00" },
{ "lat": 46.894000, "lng": 1.406000, "grv": "#ffae00" },
{ "lat": 46.745000, "lng": 1.828000, "grv": "#ffae00" },
{ "lat": 46.954000, "lng": 1.992000, "grv": "#ffae00" },
{ "lat": 46.422000, "lng": 1.366000, "grv": "#ffae00" },
{ "lat": 46.894000, "lng": 1.426000, "grv": "#ffae00" },
{ "lat": 46.942000, "lng": 1.230000, "grv": "#ffae00" },
{ "lat": 46.852000, "lng": 1.537000, "grv": "#ffae00" },
{ "lat": 46.821000, "lng": 1.206000, "grv": "#ffae00" },
{ "lat": 46.686000, "lng": 1.042000, "grv": "#ffae00" },
{ "lat": 46.446000, "lng": 1.820000, "grv": "#ffae00" },
{ "lat": 46.954000, "lng": 1.998000, "grv": "#ffae00" },
{ "lat": 46.747000, "lng": 1.412000, "grv": "#ffae00" },
{ "lat": 46.595000, "lng": 1.818000, "grv": "#ffae00" },
{ "lat": 46.441000, "lng": 1.824000, "grv": "#ffae00" },
{ "lat": 46.802000, "lng": 1.405000, "grv": "#ffae00" },
{ "lat": 46.967000, "lng": 1.734000, "grv": "#ffae00" },
{ "lat": 46.850000, "lng": 1.530000, "grv": "#ffae00" },
{ "lat": 46.482000, "lng": 1.940000, "grv": "#ffae00" },
{ "lat": 46.899000, "lng": 1.643000, "grv": "#ffae00" },
{ "lat": 46.732000, "lng": 1.379000, "grv": "#ffae00" },
{ "lat": 46.930000, "lng": 1.938000, "grv": "#ffae00" },
{ "lat": 46.486000, "lng": 1.502000, "grv": "#ffae00" },
{ "lat": 46.672000, "lng": 1.922000, "grv": "#ffae00" },
{ "lat": 46.501000, "lng": 1.620000, "grv": "#ffae00" },
{ "lat": 46.880000, "lng": 1.423000, "grv": "#ffae00" },
{ "lat": 46.481000, "lng": 1.929000, "grv": "#ffae00" },
{ "lat": 46.596000, "lng": 1.524000, "grv": "#ffae00" },
{ "lat": 46.600000, "lng": 1.500000, "grv": "#ffae00" },
{ "lat": 46.830000, "lng": 1.637000, "grv": "#ffae00" },
{ "lat": 46.815000, "lng": 1.860000, "grv": "#ffae00" },
{ "lat": 46.463000, "lng": 1.770000, "grv": "#ffae00" },
{ "lat": 46.985000, "lng": 1.978000, "grv": "#ffae00" },
{ "lat": 46.620000, "lng": 1.778000, "grv": "#ffae00" },
{ "lat": 46.870000, "lng": 1.439000, "grv": "#ffae00" },
{ "lat": 46.680000, "lng": 1.048000, "grv": "#ffae00" },
{ "lat": 46.796300, "lng": 1.708110, "grv": "#ffae00" },
{ "lat": 46.572900, "lng": 1.986950, "grv": "#ffae00" },
{ "lat": 46.762400, "lng": 1.678700, "grv": "#ffae00" },
{ "lat": 46.797700, "lng": 1.638290, "grv": "#ffae00" },
{ "lat": 46.804300, "lng": 1.691840, "grv": "#ffae00" },
{ "lat": 46.799010, "lng": 1.640310, "grv": "#ffae00" },
{ "lat": 46.810800, "lng": 1.700280, "grv": "#ffae00" },
{ "lat": 46.812400, "lng": 1.697920, "grv": "#ffae00" },
{ "lat": 46.771500, "lng": 1.661360, "grv": "#ffae00" },
{ "lat": 46.511900, "lng": 1.993930, "grv": "#ffae00" },
{ "lat": 46.585100, "lng": 1.985000, "grv": "#ffae00" },
{ "lat": 46.808200, "lng": 1.703880, "grv": "#ffae00" },
{ "lat": 46.791600, "lng": 1.595960, "grv": "#ffae00" },
{ "lat": 46.888100, "lng": 1.432790, "grv": "#ffae00" },
{ "lat": 46.810100, "lng": 1.639750, "grv": "#ffae00" },
{ "lat": 46.598300, "lng": 1.733020, "grv": "#ffae00" },
{ "lat": 46.877700, "lng": 1.657900, "grv": "#ffae00" },
{ "lat": 46.975300, "lng": 1.603080, "grv": "#ffae00" },
{ "lat": 46.452700, "lng": 1.434730, "grv": "#ffae00" },
{ "lat": 46.797700, "lng": 1.728150, "grv": "#ffae00" },
{ "lat": 46.796000, "lng": 1.353000, "grv": "#ffae00" },
{ "lat": 46.698600, "lng": 1.586530, "grv": "#ffae00" },
{ "lat": 46.821800, "lng": 1.694660, "grv": "#ffae00" },
{ "lat": 46.783900, "lng": 1.690230, "grv": "#ffae00" },
{ "lat": 46.976200, "lng": 1.175890, "grv": "#ffae00" },
{ "lat": 46.467100, "lng": 1.911000, "grv": "#ffae00" },
{ "lat": 46.802300, "lng": 1.703880, "grv": "#ffae00" },
{ "lat": 46.941700, "lng": 1.751200, "grv": "#ffae00" },
{ "lat": 46.540300, "lng": 1.741280, "grv": "#ffae00" },
{ "lat": 46.585300, "lng": 1.987500, "grv": "#ffae00" },
{ "lat": 46.481600, "lng": 1.198410, "grv": "#ffae00" },
{ "lat": 46.803600, "lng": 1.709300, "grv": "#ffae00" },
{ "lat": 46.945400, "lng": 1.995410, "grv": "#ffae00" },
{ "lat": 46.617300, "lng": 1.367910, "grv": "#ffae00" },
{ "lat": 46.608200, "lng": 1.918410, "grv": "#ffae00" },
{ "lat": 46.600300, "lng": 1.978870, "grv": "#ffae00" },
{ "lat": 46.822780, "lng": 1.656460, "grv": "#ffae00" },
{ "lat": 46.814600, "lng": 1.280990, "grv": "#ffae00" },
{ "lat": 46.596100, "lng": 1.499740, "grv": "#ffae00" },
{ "lat": 46.654200, "lng": 1.087850, "grv": "#ffae00" },
{ "lat": 46.771600, "lng": 1.660030, "grv": "#ffae00" },
{ "lat": 46.433600, "lng": 1.610230, "grv": "#ffae00" },
{ "lat": 46.827900, "lng": 1.703830, "grv": "#ffae00" },
{ "lat": 46.556300, "lng": 1.560000, "grv": "#ffae00" },
{ "lat": 46.983100, "lng": 1.412210, "grv": "#ffae00" },
{ "lat": 46.602000, "lng": 1.523840, "grv": "#ffae00" },
{ "lat": 46.808900, "lng": 1.705000, "grv": "#ffae00" },
{ "lat": 46.763700, "lng": 1.721720, "grv": "#ffae00" },
{ "lat": 46.766800, "lng": 1.797980, "grv": "#ffae00" },
{ "lat": 46.636800, "lng": 1.386480, "grv": "#ffae00" },
{ "lat": 46.961300, "lng": 1.271640, "grv": "#ffae00" },
{ "lat": 46.816200, "lng": 1.601940, "grv": "#ffae00" },
{ "lat": 46.588400, "lng": 1.836410, "grv": "#ffae00" },
{ "lat": 46.506100, "lng": 1.563490, "grv": "#ffae00" },
{ "lat": 46.504900, "lng": 1.540620, "grv": "#ffae00" },
{ "lat": 46.956800, "lng": 1.999360, "grv": "#ffae00" },
{ "lat": 46.629800, "lng": 1.550520, "grv": "#ffae00" },
{ "lat": 46.951100, "lng": 1.994310, "grv": "#ffae00" },
{ "lat": 46.749700, "lng": 1.132130, "grv": "#ffae00" },
{ "lat": 46.591600, "lng": 1.169190, "grv": "#ffae00" },
{ "lat": 46.796300, "lng": 1.699070, "grv": "#ffae00" },
{ "lat": 46.806800, "lng": 1.688850, "grv": "#ffae00" },
{ "lat": 46.802800, "lng": 1.717200, "grv": "#ffae00" },
{ "lat": 46.696800, "lng": 1.468850, "grv": "#ffae00" },
{ "lat": 46.803560, "lng": 1.665580, "grv": "#ffae00" },
{ "lat": 46.818400, "lng": 1.688540, "grv": "#ffae00" },
{ "lat": 46.585200, "lng": 1.493790, "grv": "#ffae00" },
{ "lat": 46.629500, "lng": 1.245170, "grv": "#ffae00" },
{ "lat": 46.944100, "lng": 1.973320, "grv": "#ffae00" },
{ "lat": 46.944400, "lng": 1.978470, "grv": "#ffae00" },
{ "lat": 46.941900, "lng": 1.226430, "grv": "#ffae00" },
{ "lat": 46.392600, "lng": 1.450830, "grv": "#ffae00" },
{ "lat": 46.470100, "lng": 1.655670, "grv": "#ffae00" },
{ "lat": 46.598300, "lng": 1.600770, "grv": "#ffae00" },
{ "lat": 46.819300, "lng": 1.697300, "grv": "#ffae00" },
{ "lat": 46.668600, "lng": 1.091660, "grv": "#ffae00" },
{ "lat": 46.987700, "lng": 1.172040, "grv": "#ffae00" },
{ "lat": 46.804400, "lng": 1.699140, "grv": "#ffae00" },
{ "lat": 46.703900, "lng": 1.750680, "grv": "#ffae00" },
{ "lat": 46.889200, "lng": 1.421730, "grv": "#ffae00" },
{ "lat": 46.576000, "lng": 1.866000, "grv": "#ffae00" },
{ "lat": 46.811000, "lng": 1.678630, "grv": "#ffae00" },
{ "lat": 46.629400, "lng": 1.054410, "grv": "#ffae00" },
{ "lat": 46.859900, "lng": 1.169070, "grv": "#ffae00" },
{ "lat": 46.820300, "lng": 1.676640, "grv": "#ffae00" },
{ "lat": 46.915300, "lng": 1.482740, "grv": "#ffae00" },
{ "lat": 46.919000, "lng": 1.771520, "grv": "#ffae00" },
{ "lat": 46.860000, "lng": 1.782460, "grv": "#ffae00" },
{ "lat": 46.684300, "lng": 1.040580, "grv": "#ffae00" },
{ "lat": 46.992100, "lng": 1.433480, "grv": "#ffae00" },
{ "lat": 46.809000, "lng": 1.681050, "grv": "#ffae00" },
{ "lat": 46.889200, "lng": 1.421730, "grv": "#ffae00" },
{ "lat": 46.820800, "lng": 1.669950, "grv": "#ffae00" },
{ "lat": 46.609200, "lng": 1.505790, "grv": "#ffae00" },
{ "lat": 46.491300, "lng": 1.998600, "grv": "#ffae00" },
{ "lat": 46.559500, "lng": 1.155360, "grv": "#ffae00" },
{ "lat": 46.874900, "lng": 1.391070, "grv": "#ffae00" },
{ "lat": 46.645200, "lng": 1.046750, "grv": "#ffae00" },
{ "lat": 46.826670, "lng": 1.701130, "grv": "#ffae00" },
{ "lat": 46.593100, "lng": 1.515110, "grv": "#ffae00" },
{ "lat": 46.485400, "lng": 1.440350, "grv": "#ffae00" },
{ "lat": 46.816900, "lng": 1.696950, "grv": "#ffae00" },
{ "lat": 46.830200, "lng": 1.454000, "grv": "#ffae00" },
{ "lat": 46.904800, "lng": 1.887890, "grv": "#ffae00" },
{ "lat": 46.689800, "lng": 1.754070, "grv": "#ffae00" },
{ "lat": 46.635100, "lng": 1.452610, "grv": "#ffae00" },
{ "lat": 46.845500, "lng": 1.708960, "grv": "#ffae00" },
{ "lat": 46.851100, "lng": 1.042240, "grv": "#ffae00" },
{ "lat": 46.803700, "lng": 1.656080, "grv": "#ffae00" },
{ "lat": 46.818100, "lng": 1.694970, "grv": "#ffae00" },
{ "lat": 46.799500, "lng": 1.704490, "grv": "#ffae00" },
{ "lat": 46.847000, "lng": 1.225240, "grv": "#ffae00" },
{ "lat": 46.821400, "lng": 1.663410, "grv": "#ffae00" },
{ "lat": 46.800000, "lng": 1.712820, "grv": "#ffae00" },
{ "lat": 46.691700, "lng": 1.806870, "grv": "#ffae00" },
{ "lat": 46.788000, "lng": 1.703690, "grv": "#ffae00" },
{ "lat": 46.599600, "lng": 1.498960, "grv": "#ffae00" },
{ "lat": 46.986300, "lng": 1.176080, "grv": "#ffae00" },
{ "lat": 46.915700, "lng": 1.162430, "grv": "#ffae00" },
{ "lat": 46.808200, "lng": 1.678040, "grv": "#ffae00" },
{ "lat": 46.631400, "lng": 1.470810, "grv": "#ffae00" },
{ "lat": 46.828200, "lng": 1.711380, "grv": "#ffae00" },
{ "lat": 46.989500, "lng": 1.171310, "grv": "#ffae00" },
{ "lat": 46.919000, "lng": 1.399430, "grv": "#ffae00" },
{ "lat": 46.446000, "lng": 1.388770, "grv": "#ffae00" },
{ "lat": 46.536000, "lng": 1.602510, "grv": "#ffae00" },
{ "lat": 46.428000, "lng": 1.007000, "grv": "#ffae00" },
{ "lat": 46.448000, "lng": 1.042000, "grv": "#ffae00" },
{ "lat": 46.402000, "lng": 1.097000, "grv": "#ffae00" },
{ "lat": 46.475000, "lng": 1.059000, "grv": "#ffae00" },
{ "lat": 46.349000, "lng": 1.365000, "grv": "#ffae00" },
{ "lat": 46.129000, "lng": 1.372000, "grv": "#ffae00" },
{ "lat": 46.187000, "lng": 1.292000, "grv": "#ffae00" },
{ "lat": 46.170000, "lng": 1.215000, "grv": "#ffae00" },
{ "lat": 46.210000, "lng": 1.160000, "grv": "#ffae00" },
{ "lat": 46.055000, "lng": 1.412000, "grv": "#ffae00" },
{ "lat": 46.222000, "lng": 1.165000, "grv": "#ffae00" },
{ "lat": 46.047000, "lng": 1.123000, "grv": "#ffae00" },
{ "lat": 46.090000, "lng": 1.479000, "grv": "#ffae00" },
{ "lat": 46.198000, "lng": 1.170000, "grv": "#ffae00" },
{ "lat": 46.042000, "lng": 1.394000, "grv": "#ffae00" },
{ "lat": 46.035000, "lng": 1.337000, "grv": "#ffae00" },
{ "lat": 46.131000, "lng": 1.091000, "grv": "#ffae00" },
{ "lat": 46.127000, "lng": 1.050000, "grv": "#ffae00" },
{ "lat": 46.001000, "lng": 1.462000, "grv": "#ffae00" },
{ "lat": 46.157000, "lng": 1.121000, "grv": "#ffae00" },
{ "lat": 46.123000, "lng": 1.265000, "grv": "#ffae00" },
{ "lat": 46.016000, "lng": 1.485000, "grv": "#ffae00" },
{ "lat": 46.069000, "lng": 1.115000, "grv": "#ffae00" },
{ "lat": 46.106000, "lng": 1.352000, "grv": "#ffae00" },
{ "lat": 46.001000, "lng": 1.321000, "grv": "#ffae00" },
{ "lat": 46.078000, "lng": 1.477000, "grv": "#ffae00" },
{ "lat": 46.204000, "lng": 1.359000, "grv": "#ffae00" },
{ "lat": 46.231000, "lng": 1.004000, "grv": "#ffae00" },
{ "lat": 46.333000, "lng": 1.180000, "grv": "#ffae00" },
{ "lat": 46.116000, "lng": 1.062000, "grv": "#ffae00" },
{ "lat": 46.357000, "lng": 1.106000, "grv": "#ffae00" },
{ "lat": 46.070000, "lng": 1.114000, "grv": "#ffae00" },
{ "lat": 46.254000, "lng": 1.376000, "grv": "#ffae00" },
{ "lat": 46.183600, "lng": 1.342570, "grv": "#ffae00" },
{ "lat": 46.065100, "lng": 1.114570, "grv": "#ffae00" },
{ "lat": 46.177000, "lng": 1.371960, "grv": "#ffae00" },
{ "lat": 46.138300, "lng": 1.056600, "grv": "#ffae00" },
{ "lat": 46.011500, "lng": 1.462120, "grv": "#ffae00" },
{ "lat": 46.071300, "lng": 1.359730, "grv": "#ffae00" },
{ "lat": 46.064400, "lng": 1.115220, "grv": "#ffae00" },
{ "lat": 46.197100, "lng": 1.286580, "grv": "#ffae00" },
{ "lat": 46.140200, "lng": 1.097920, "grv": "#ffae00" },
{ "lat": 46.438000, "lng": 1.868000, "grv": "#ffae00" },
{ "lat": 46.364000, "lng": 1.990000, "grv": "#ffae00" },
{ "lat": 46.261000, "lng": 1.435000, "grv": "#ffae00" },
{ "lat": 46.397000, "lng": 1.616000, "grv": "#ffae00" },
{ "lat": 46.108000, "lng": 1.842000, "grv": "#ffae00" },
{ "lat": 46.093000, "lng": 1.562000, "grv": "#ffae00" },
{ "lat": 46.242000, "lng": 1.486000, "grv": "#ffae00" },
{ "lat": 46.224000, "lng": 1.700000, "grv": "#ffae00" },
{ "lat": 46.486000, "lng": 1.507000, "grv": "#ffae00" },
{ "lat": 46.988000, "lng": 1.613000, "grv": "#ffae00" },
{ "lat": 46.390000, "lng": 1.450000, "grv": "#ffae00" },
{ "lat": 46.868000, "lng": 1.771000, "grv": "#ffae00" },
{ "lat": 46.602000, "lng": 1.524000, "grv": "#ffae00" },
{ "lat": 46.470000, "lng": 1.670000, "grv": "#ffae00" },
{ "lat": 46.892000, "lng": 1.421000, "grv": "#ffae00" },
{ "lat": 46.750000, "lng": 1.620000, "grv": "#ffae00" },
{ "lat": 46.523000, "lng": 1.147000, "grv": "#ffae00" },
{ "lat": 46.516000, "lng": 1.599000, "grv": "#ffae00" },
{ "lat": 46.529000, "lng": 1.992000, "grv": "#ffae00" },
{ "lat": 46.980000, "lng": 1.960000, "grv": "#ffae00" },
{ "lat": 46.837000, "lng": 1.352000, "grv": "#ffae00" },
{ "lat": 46.737000, "lng": 1.893000, "grv": "#ffae00" },
{ "lat": 46.749000, "lng": 1.044000, "grv": "#ffae00" },
{ "lat": 46.937000, "lng": 1.336000, "grv": "#ffae00" },
{ "lat": 46.874700, "lng": 1.721770, "grv": "#ffae00" },
{ "lat": 46.933000, "lng": 1.385460, "grv": "#ffae00" },
{ "lat": 46.461800, "lng": 1.498130, "grv": "#ffae00" },
{ "lat": 46.759400, "lng": 1.809210, "grv": "#ffae00" },
{ "lat": 46.459300, "lng": 1.600580, "grv": "#ffae00" },
{ "lat": 46.816800, "lng": 1.677840, "grv": "#ffae00" },
{ "lat": 46.598200, "lng": 1.783790, "grv": "#ffae00" },
{ "lat": 46.511600, "lng": 1.993980, "grv": "#ffae00" },
{ "lat": 46.583900, "lng": 1.988320, "grv": "#ffae00" },
{ "lat": 46.630000, "lng": 1.549340, "grv": "#ffae00" },
{ "lat": 46.454200, "lng": 1.495380, "grv": "#ffae00" },
{ "lat": 46.628300, "lng": 1.149980, "grv": "#ffae00" },
{ "lat": 46.578600, "lng": 1.880460, "grv": "#ffae00" },
{ "lat": 46.652900, "lng": 1.913650, "grv": "#ffae00" },
{ "lat": 46.571000, "lng": 1.859520, "grv": "#ffae00" },
{ "lat": 46.877800, "lng": 1.719000, "grv": "#ffae00" },
{ "lat": 46.944600, "lng": 1.316900, "grv": "#ffae00" },
{ "lat": 46.572000, "lng": 1.154740, "grv": "#ffae00" },
{ "lat": 46.605800, "lng": 1.502190, "grv": "#ffae00" },
{ "lat": 46.861400, "lng": 1.710270, "grv": "#ffae00" },
{ "lat": 46.809400, "lng": 1.703370, "grv": "#ffae00" },
{ "lat": 46.593000, "lng": 1.497830, "grv": "#ffae00" },
{ "lat": 46.791700, "lng": 1.712040, "grv": "#ffae00" },
{ "lat": 46.781400, "lng": 1.744290, "grv": "#ffae00" },
{ "lat": 46.500300, "lng": 1.451890, "grv": "#ffae00" },
{ "lat": 46.196000, "lng": 1.255000, "grv": "#ffae00" },
{ "lat": 46.070000, "lng": 1.304000, "grv": "#ffae00" },
{ "lat": 46.151000, "lng": 1.370000, "grv": "#ffae00" },
{ "lat": 46.136000, "lng": 1.373000, "grv": "#ffae00" },
{ "lat": 46.218000, "lng": 1.148000, "grv": "#ffae00" },
{ "lat": 46.340000, "lng": 1.347000, "grv": "#ffae00" },
{ "lat": 46.202000, "lng": 1.308000, "grv": "#ffae00" },
{ "lat": 46.182900, "lng": 1.380310, "grv": "#ffae00" },
{ "lat": 46.299000, "lng": 1.474000, "grv": "#ffae00" },
{ "lat": 46.843000, "lng": 1.577000, "grv": "#ffae00" },
{ "lat": 46.800000, "lng": 1.665000, "grv": "#ffae00" },
{ "lat": 46.740600, "lng": 1.613990, "grv": "#ffae00" },
{ "lat": 46.727600, "lng": 1.733460, "grv": "#ffae00" },
{ "lat": 46.788700, "lng": 1.691310, "grv": "#ffae00" },
{ "lat": 46.587000, "lng": 1.989000, "grv": "#ffae00" },
{ "lat": 46.439000, "lng": 1.825000, "grv": "#ffae00" },
{ "lat": 46.788000, "lng": 1.703690, "grv": "#ffae00" },
{ "lat": 46.920500, "lng": 1.126400, "grv": "#ffae00" },
{ "lat": 46.471700, "lng": 1.613890, "grv": "#ffae00" },
{ "lat": 46.771900, "lng": 1.656710, "grv": "#ffae00" },
{ "lat": 46.154000, "lng": 1.909000, "grv": "#ffae00" },
{ "lat": 46.633000, "lng": 1.163000, "grv": "#ffae00" },
{ "lat": 46.788000, "lng": 1.703690, "grv": "#ffae00" },
{ "lat": 46.236000, "lng": 1.488000, "grv": "#ffae00" },
{ "lat": 46.282000, "lng": 1.670000, "grv": "#ffae00" },
{ "lat": 46.254000, "lng": 1.845000, "grv": "#ffae00" },
{ "lat": 46.212000, "lng": 1.400000, "grv": "#ffae00" },
{ "lat": 46.065000, "lng": 1.694000, "grv": "#ffae00" },
{ "lat": 46.370000, "lng": 1.490000, "grv": "#ffae00" },
{ "lat": 46.289000, "lng": 1.473000, "grv": "#ffae00" },
{ "lat": 46.118000, "lng": 1.978000, "grv": "#ffae00" },
{ "lat": 46.392000, "lng": 1.452000, "grv": "#ffae00" },
{ "lat": 46.977000, "lng": 1.615000, "grv": "#ffae00" },
{ "lat": 46.858000, "lng": 1.523000, "grv": "#ffae00" },
{ "lat": 46.610000, "lng": 1.133000, "grv": "#ffae00" },
{ "lat": 46.935000, "lng": 1.316000, "grv": "#ffae00" },
{ "lat": 46.636000, "lng": 1.138000, "grv": "#ffae00" },
{ "lat": 46.654000, "lng": 1.948000, "grv": "#ffae00" },
{ "lat": 46.933000, "lng": 1.972000, "grv": "#ffae00" },
{ "lat": 46.619000, "lng": 1.536000, "grv": "#ffae00" },
{ "lat": 46.431000, "lng": 1.574000, "grv": "#ffae00" },
{ "lat": 46.868000, "lng": 1.529000, "grv": "#ffae00" },
{ "lat": 46.702000, "lng": 1.706000, "grv": "#ffae00" },
{ "lat": 46.615900, "lng": 1.538310, "grv": "#ffae00" },
{ "lat": 46.892100, "lng": 1.397500, "grv": "#ffae00" },
{ "lat": 46.611100, "lng": 1.518260, "grv": "#ffae00" },
{ "lat": 46.639300, "lng": 1.379600, "grv": "#ffae00" },
{ "lat": 46.415400, "lng": 1.467520, "grv": "#ffae00" },
{ "lat": 46.751700, "lng": 1.820720, "grv": "#ffae00" },
{ "lat": 46.840700, "lng": 1.570360, "grv": "#ffae00" },
{ "lat": 46.898100, "lng": 1.419550, "grv": "#ffae00" },
{ "lat": 46.932800, "lng": 1.262070, "grv": "#ffae00" },
{ "lat": 46.009000, "lng": 1.206000, "grv": "#ffae00" },
{ "lat": 46.111000, "lng": 1.087000, "grv": "#ffae00" },
{ "lat": 46.124000, "lng": 1.475000, "grv": "#ffae00" },
{ "lat": 46.322400, "lng": 1.205030, "grv": "#ffae00" },
{ "lat": 46.313100, "lng": 1.307890, "grv": "#ffae00" },
{ "lat": 46.139400, "lng": 1.286690, "grv": "#ffae00" },
{ "lat": 46.184000, "lng": 1.847000, "grv": "#ffae00" },
{ "lat": 46.160000, "lng": 1.640000, "grv": "#ffae00" },
{ "lat": 46.318000, "lng": 1.663000, "grv": "#ffae00" },
{ "lat": 46.340000, "lng": 1.657000, "grv": "#ffae00" },
{ "lat": 46.166000, "lng": 1.898000, "grv": "#ffae00" },
{ "lat": 46.724000, "lng": 1.598000, "grv": "#ffae00" },
{ "lat": 46.803000, "lng": 1.409000, "grv": "#ffae00" },
{ "lat": 46.925900, "lng": 1.285250, "grv": "#ffae00" },
{ "lat": 46.934900, "lng": 1.255100, "grv": "#ffae00" },
{ "lat": 46.118000, "lng": 1.061000, "grv": "#ffae00" },
{ "lat": 46.069000, "lng": 1.302000, "grv": "#ffae00" },
{ "lat": 46.742000, "lng": 1.019000, "grv": "#ffae00" },
{ "lat": 46.098000, "lng": 1.082000, "grv": "#ffae00" },
{ "lat": 46.064000, "lng": 1.118000, "grv": "#ffae00" },
{ "lat": 46.932200, "lng": 1.835200, "grv": "#ffae00" },
{ "lat": 46.406300, "lng": 1.460410, "grv": "#ffae00" },
{ "lat": 46.079000, "lng": 1.468000, "grv": "#ffae00" },
{ "lat": 46.252000, "lng": 1.860000, "grv": "#ffae00" },
{ "lat": 46.925000, "lng": 1.305000, "grv": "#ffae00" },
{ "lat": 46.834800, "lng": 1.677320, "grv": "#ffae00" },
{ "lat": 46.712500, "lng": 1.593660, "grv": "#ffae00" },
{ "lat": 46.171000, "lng": 1.207000, "grv": "#ffae00" },
{ "lat": 46.129000, "lng": 1.028000, "grv": "#ffae00" },
{ "lat": 46.055000, "lng": 1.490000, "grv": "#ffae00" },
{ "lat": 46.527000, "lng": 1.506000, "grv": "#ffae00" },
{ "lat": 46.842000, "lng": 1.585000, "grv": "#ffae00" },
{ "lat": 46.048000, "lng": 1.019000, "grv": "#ffae00" },
{ "lat": 46.575000, "lng": 1.501000, "grv": "#ffae00" },
{ "lat": 46.041000, "lng": 1.709000, "grv": "#ffae00" },
{ "lat": 46.181700, "lng": 1.379860, "grv": "#ffae00" },
{ "lat": 46.201000, "lng": 1.785000, "grv": "#ff0000" },
{ "lat": 46.130000, "lng": 1.940000, "grv": "#ff0000" },
{ "lat": 46.159000, "lng": 1.903000, "grv": "#ff0000" },
{ "lat": 46.092000, "lng": 1.796000, "grv": "#ff0000" },
{ "lat": 46.133000, "lng": 1.954000, "grv": "#ff0000" },
{ "lat": 46.219000, "lng": 1.386000, "grv": "#ff0000" },
{ "lat": 46.306000, "lng": 1.913000, "grv": "#ff0000" },
{ "lat": 46.177000, "lng": 1.833000, "grv": "#ff0000" },
{ "lat": 46.360000, "lng": 1.490000, "grv": "#ff0000" },
{ "lat": 46.260000, "lng": 1.923000, "grv": "#ff0000" },
{ "lat": 46.255000, "lng": 1.718000, "grv": "#ff0000" },
{ "lat": 46.136000, "lng": 1.938000, "grv": "#ff0000" },
{ "lat": 46.338000, "lng": 1.693000, "grv": "#ff0000" },
{ "lat": 46.113000, "lng": 1.985000, "grv": "#ff0000" },
{ "lat": 46.372000, "lng": 1.564000, "grv": "#ff0000" },
{ "lat": 46.303000, "lng": 1.646000, "grv": "#ff0000" },
{ "lat": 46.425000, "lng": 1.923000, "grv": "#ff0000" },
{ "lat": 46.343000, "lng": 1.654000, "grv": "#ff0000" },
{ "lat": 46.010000, "lng": 1.862000, "grv": "#ff0000" },
{ "lat": 46.499000, "lng": 1.362000, "grv": "#ff0000" },
{ "lat": 46.440000, "lng": 1.480000, "grv": "#ff0000" },
{ "lat": 46.803000, "lng": 1.913000, "grv": "#ff0000" },
{ "lat": 46.529000, "lng": 1.474000, "grv": "#ff0000" },
{ "lat": 46.524000, "lng": 1.635000, "grv": "#ff0000" },
{ "lat": 46.424000, "lng": 1.248000, "grv": "#ff0000" },
{ "lat": 46.593000, "lng": 1.274000, "grv": "#ff0000" },
{ "lat": 46.921000, "lng": 1.123000, "grv": "#ff0000" },
{ "lat": 46.900000, "lng": 1.421000, "grv": "#ff0000" },
{ "lat": 46.894000, "lng": 1.054000, "grv": "#ff0000" },
{ "lat": 46.610000, "lng": 1.708000, "grv": "#ff0000" },
{ "lat": 46.586000, "lng": 1.988000, "grv": "#ff0000" },
{ "lat": 46.652000, "lng": 1.034000, "grv": "#ff0000" },
{ "lat": 46.464000, "lng": 1.570000, "grv": "#ff0000" },
{ "lat": 46.684000, "lng": 1.503000, "grv": "#ff0000" },
{ "lat": 46.649000, "lng": 1.052000, "grv": "#ff0000" },
{ "lat": 46.665000, "lng": 1.132000, "grv": "#ff0000" },
{ "lat": 46.925000, "lng": 1.305000, "grv": "#ff0000" },
{ "lat": 46.602000, "lng": 1.787000, "grv": "#ff0000" },
{ "lat": 46.575000, "lng": 1.206000, "grv": "#ff0000" },
{ "lat": 46.942000, "lng": 1.967000, "grv": "#ff0000" },
{ "lat": 46.613000, "lng": 1.505000, "grv": "#ff0000" },
{ "lat": 46.946000, "lng": 1.985000, "grv": "#ff0000" },
{ "lat": 46.579000, "lng": 1.849000, "grv": "#ff0000" },
{ "lat": 46.942200, "lng": 1.976040, "grv": "#ff0000" },
{ "lat": 46.746600, "lng": 1.828280, "grv": "#ff0000" },
{ "lat": 46.708400, "lng": 1.586210, "grv": "#ff0000" },
{ "lat": 46.572700, "lng": 1.936130, "grv": "#ff0000" },
{ "lat": 46.894900, "lng": 1.484750, "grv": "#ff0000" },
{ "lat": 46.788000, "lng": 1.672780, "grv": "#ff0000" },
{ "lat": 46.674800, "lng": 1.098110, "grv": "#ff0000" },
{ "lat": 46.859500, "lng": 1.332500, "grv": "#ff0000" },
{ "lat": 46.647800, "lng": 1.031570, "grv": "#ff0000" },
{ "lat": 46.474500, "lng": 1.614630, "grv": "#ff0000" },
{ "lat": 46.409800, "lng": 1.581280, "grv": "#ff0000" },
{ "lat": 46.434100, "lng": 1.828020, "grv": "#ff0000" },
{ "lat": 46.379200, "lng": 1.446670, "grv": "#ff0000" },
{ "lat": 46.240000, "lng": 1.050000, "grv": "#ff0000" },
{ "lat": 46.196000, "lng": 1.250000, "grv": "#ff0000" },
{ "lat": 46.341000, "lng": 1.199000, "grv": "#ff0000" },
{ "lat": 46.263000, "lng": 1.395000, "grv": "#ff0000" },
{ "lat": 46.357000, "lng": 1.173000, "grv": "#ff0000" },
{ "lat": 46.255000, "lng": 1.259000, "grv": "#ff0000" },
{ "lat": 46.108000, "lng": 1.373000, "grv": "#ff0000" },
{ "lat": 46.160000, "lng": 1.130000, "grv": "#ff0000" },
{ "lat": 46.083000, "lng": 1.095000, "grv": "#ff0000" },
{ "lat": 46.062000, "lng": 1.121000, "grv": "#ff0000" },
{ "lat": 46.125600, "lng": 1.073740, "grv": "#ff0000" },
{ "lat": 46.129500, "lng": 1.033500, "grv": "#ff0000" },
{ "lat": 46.902000, "lng": 1.267000, "grv": "#ff0000" },
{ "lat": 46.987000, "lng": 1.175000, "grv": "#ff0000" },
{ "lat": 46.655100, "lng": 1.089010, "grv": "#ff0000" },
{ "lat": 46.820400, "lng": 1.669170, "grv": "#ff0000" },
{ "lat": 46.915800, "lng": 1.987350, "grv": "#ff0000" },
{ "lat": 46.970600, "lng": 1.993750, "grv": "#ff0000" },
{ "lat": 46.593300, "lng": 1.553870, "grv": "#ff0000" },
{ "lat": 46.878000, "lng": 1.814000, "grv": "#ff0000" },
{ "lat": 46.395800, "lng": 1.400910, "grv": "#ff0000" },
{ "lat": 46.978000, "lng": 1.177000, "grv": "#ff0000" },
{ "lat": 46.420000, "lng": 1.589000, "grv": "#ff0000" },
{ "lat": 46.963000, "lng": 1.725000, "grv": "#ff0000" },
{ "lat": 46.912000, "lng": 1.962000, "grv": "#ff0000" },
{ "lat": 46.768200, "lng": 1.641820, "grv": "#ff0000" },
{ "lat": 46.599100, "lng": 1.976790, "grv": "#ff0000" },
{ "lat": 46.792700, "lng": 1.991110, "grv": "#ff0000" },
{ "lat": 46.198000, "lng": 1.278000, "grv": "#ff0000" },
{ "lat": 46.219000, "lng": 1.125000, "grv": "#ff0000" },
{ "lat": 46.196000, "lng": 1.257000, "grv": "#ff0000" },
{ "lat": 46.022000, "lng": 1.295000, "grv": "#ff0000" },
{ "lat": 46.218000, "lng": 1.641000, "grv": "#ff0000" },
{ "lat": 46.741000, "lng": 1.025000, "grv": "#ff0000" },
{ "lat": 46.834100, "lng": 1.286410, "grv": "#ff0000" },
{ "lat": 46.288000, "lng": 1.613000, "grv": "#ff0000" },
{ "lat": 46.329000, "lng": 1.528000, "grv": "#ff0000" },
{ "lat": 46.571000, "lng": 1.755000, "grv": "#ff0000" },
{ "lat": 46.909000, "lng": 1.636000, "grv": "#ff0000" },
{ "lat": 46.879000, "lng": 1.722000, "grv": "#ff0000" },
{ "lat": 46.696500, "lng": 1.887180, "grv": "#ff0000" },
{ "lat": 46.826000, "lng": 1.503000, "grv": "#ff0000" },
{ "lat": 46.906000, "lng": 1.879000, "grv": "#ff0000" },
{ "lat": 46.547800, "lng": 1.553250, "grv": "#ff0000" },
{ "lat": 46.966000, "lng": 1.983000, "grv": "#ff0000" },
{ "lat": 46.919700, "lng": 1.922970, "grv": "#ff0000" },
{ "lat": 46.207000, "lng": 1.346000, "grv": "#ff0000" },
{} ] }
