{ "accidents" : [
{ "lat": 43.064000, "lng": 2.221000, "grv": "#f6ff00" },
{ "lat": 43.134000, "lng": 2.654000, "grv": "#f6ff00" },
{ "lat": 43.199000, "lng": 2.301000, "grv": "#f6ff00" },
{ "lat": 43.290000, "lng": 2.832000, "grv": "#f6ff00" },
{ "lat": 43.032000, "lng": 2.988000, "grv": "#f6ff00" },
{ "lat": 43.315000, "lng": 2.496000, "grv": "#f6ff00" },
{ "lat": 43.234000, "lng": 2.642000, "grv": "#f6ff00" },
{ "lat": 43.242000, "lng": 2.198000, "grv": "#f6ff00" },
{ "lat": 43.270000, "lng": 2.870000, "grv": "#f6ff00" },
{ "lat": 43.294000, "lng": 2.047000, "grv": "#f6ff00" },
{ "lat": 43.042000, "lng": 2.343000, "grv": "#f6ff00" },
{ "lat": 43.369000, "lng": 2.253000, "grv": "#f6ff00" },
{ "lat": 43.127000, "lng": 2.295000, "grv": "#f6ff00" },
{ "lat": 43.177000, "lng": 2.326000, "grv": "#f6ff00" },
{ "lat": 43.322000, "lng": 2.010000, "grv": "#f6ff00" },
{ "lat": 43.273000, "lng": 2.036000, "grv": "#f6ff00" },
{ "lat": 43.196000, "lng": 2.054000, "grv": "#f6ff00" },
{ "lat": 43.069000, "lng": 2.219000, "grv": "#f6ff00" },
{ "lat": 43.033000, "lng": 2.979000, "grv": "#f6ff00" },
{ "lat": 43.070000, "lng": 2.215000, "grv": "#f6ff00" },
{ "lat": 43.111000, "lng": 2.528000, "grv": "#f6ff00" },
{ "lat": 43.132000, "lng": 2.532000, "grv": "#f6ff00" },
{ "lat": 43.230000, "lng": 2.790000, "grv": "#f6ff00" },
{ "lat": 43.157000, "lng": 2.973000, "grv": "#f6ff00" },
{ "lat": 43.274000, "lng": 2.040000, "grv": "#f6ff00" },
{ "lat": 43.287000, "lng": 2.586000, "grv": "#f6ff00" },
{ "lat": 43.129000, "lng": 2.957000, "grv": "#f6ff00" },
{ "lat": 43.031000, "lng": 2.988000, "grv": "#f6ff00" },
{ "lat": 43.034000, "lng": 2.978000, "grv": "#f6ff00" },
{ "lat": 43.204000, "lng": 2.765000, "grv": "#f6ff00" },
{ "lat": 43.270000, "lng": 2.719000, "grv": "#f6ff00" },
{ "lat": 43.962000, "lng": 2.884000, "grv": "#f6ff00" },
{ "lat": 43.962000, "lng": 2.881000, "grv": "#f6ff00" },
{ "lat": 43.880000, "lng": 2.778000, "grv": "#f6ff00" },
{ "lat": 43.828000, "lng": 2.877000, "grv": "#f6ff00" },
{ "lat": 43.774000, "lng": 2.949000, "grv": "#f6ff00" },
{ "lat": 43.959000, "lng": 2.887000, "grv": "#f6ff00" },
{ "lat": 43.894000, "lng": 2.594000, "grv": "#f6ff00" },
{ "lat": 43.810000, "lng": 2.860000, "grv": "#f6ff00" },
{ "lat": 43.962000, "lng": 2.884000, "grv": "#f6ff00" },
{ "lat": 43.962000, "lng": 2.884000, "grv": "#f6ff00" },
{ "lat": 43.963000, "lng": 2.885000, "grv": "#f6ff00" },
{ "lat": 43.947000, "lng": 2.828000, "grv": "#f6ff00" },
{ "lat": 43.962000, "lng": 2.872000, "grv": "#f6ff00" },
{ "lat": 43.945000, "lng": 2.896000, "grv": "#f6ff00" },
{ "lat": 43.966000, "lng": 2.739000, "grv": "#f6ff00" },
{ "lat": 43.467000, "lng": 2.007000, "grv": "#f6ff00" },
{ "lat": 43.455900, "lng": 2.008850, "grv": "#f6ff00" },
{ "lat": 43.687000, "lng": 2.966000, "grv": "#f6ff00" },
{ "lat": 43.415000, "lng": 2.972000, "grv": "#f6ff00" },
{ "lat": 43.689000, "lng": 2.921000, "grv": "#f6ff00" },
{ "lat": 43.392000, "lng": 2.761000, "grv": "#f6ff00" },
{ "lat": 43.358000, "lng": 2.782000, "grv": "#f6ff00" },
{ "lat": 43.483000, "lng": 2.670000, "grv": "#f6ff00" },
{ "lat": 43.470000, "lng": 2.792000, "grv": "#f6ff00" },
{ "lat": 43.418000, "lng": 2.973000, "grv": "#f6ff00" },
{ "lat": 43.471000, "lng": 2.790000, "grv": "#f6ff00" },
{ "lat": 43.522000, "lng": 2.990100, "grv": "#f6ff00" },
{ "lat": 43.597030, "lng": 2.950850, "grv": "#f6ff00" },
{ "lat": 43.435000, "lng": 2.979000, "grv": "#f6ff00" },
{ "lat": 43.788000, "lng": 2.147000, "grv": "#f6ff00" },
{ "lat": 43.578000, "lng": 2.010000, "grv": "#f6ff00" },
{ "lat": 43.509000, "lng": 2.352000, "grv": "#f6ff00" },
{ "lat": 43.457000, "lng": 2.049000, "grv": "#f6ff00" },
{ "lat": 43.562000, "lng": 2.180000, "grv": "#f6ff00" },
{ "lat": 43.456000, "lng": 2.062000, "grv": "#f6ff00" },
{ "lat": 43.779000, "lng": 2.077000, "grv": "#f6ff00" },
{ "lat": 43.516000, "lng": 2.331000, "grv": "#f6ff00" },
{ "lat": 43.560000, "lng": 2.580000, "grv": "#f6ff00" },
{ "lat": 43.506000, "lng": 2.407000, "grv": "#f6ff00" },
{ "lat": 43.517000, "lng": 2.325000, "grv": "#f6ff00" },
{ "lat": 43.517000, "lng": 2.328000, "grv": "#f6ff00" },
{ "lat": 43.828000, "lng": 2.185000, "grv": "#f6ff00" },
{ "lat": 43.910000, "lng": 2.183000, "grv": "#f6ff00" },
{ "lat": 43.586000, "lng": 2.184000, "grv": "#f6ff00" },
{ "lat": 43.886000, "lng": 2.101000, "grv": "#f6ff00" },
{ "lat": 43.498000, "lng": 2.428000, "grv": "#f6ff00" },
{ "lat": 43.488000, "lng": 2.130000, "grv": "#f6ff00" },
{ "lat": 43.540000, "lng": 2.100000, "grv": "#f6ff00" },
{ "lat": 43.521000, "lng": 2.312000, "grv": "#f6ff00" },
{ "lat": 43.499000, "lng": 2.157000, "grv": "#f6ff00" },
{ "lat": 43.981000, "lng": 2.381000, "grv": "#f6ff00" },
{ "lat": 43.577000, "lng": 2.136000, "grv": "#f6ff00" },
{ "lat": 43.504500, "lng": 2.380080, "grv": "#f6ff00" },
{ "lat": 43.987400, "lng": 2.262750, "grv": "#f6ff00" },
{ "lat": 43.916600, "lng": 2.279500, "grv": "#f6ff00" },
{ "lat": 43.646800, "lng": 2.517140, "grv": "#f6ff00" },
{ "lat": 43.780400, "lng": 2.104130, "grv": "#f6ff00" },
{ "lat": 43.553000, "lng": 2.181970, "grv": "#f6ff00" },
{ "lat": 43.115000, "lng": 2.273000, "grv": "#f6ff00" },
{ "lat": 43.210000, "lng": 2.791000, "grv": "#f6ff00" },
{ "lat": 43.280000, "lng": 2.887000, "grv": "#f6ff00" },
{ "lat": 43.096000, "lng": 2.231000, "grv": "#f6ff00" },
{ "lat": 43.310000, "lng": 2.130000, "grv": "#f6ff00" },
{ "lat": 43.265000, "lng": 2.138000, "grv": "#f6ff00" },
{ "lat": 43.321000, "lng": 2.508000, "grv": "#f6ff00" },
{ "lat": 43.051000, "lng": 2.135000, "grv": "#f6ff00" },
{ "lat": 43.004000, "lng": 2.251000, "grv": "#f6ff00" },
{ "lat": 43.273000, "lng": 2.681000, "grv": "#f6ff00" },
{ "lat": 43.090000, "lng": 2.620000, "grv": "#f6ff00" },
{ "lat": 43.207000, "lng": 2.272000, "grv": "#f6ff00" },
{ "lat": 43.316000, "lng": 2.957000, "grv": "#f6ff00" },
{ "lat": 43.274000, "lng": 2.895000, "grv": "#f6ff00" },
{ "lat": 43.215000, "lng": 2.453000, "grv": "#f6ff00" },
{ "lat": 43.190000, "lng": 2.919000, "grv": "#f6ff00" },
{ "lat": 43.761000, "lng": 2.916000, "grv": "#f6ff00" },
{ "lat": 43.730000, "lng": 2.930000, "grv": "#f6ff00" },
{ "lat": 43.960000, "lng": 2.858000, "grv": "#f6ff00" },
{ "lat": 43.420630, "lng": 2.955720, "grv": "#f6ff00" },
{ "lat": 43.744000, "lng": 2.166000, "grv": "#f6ff00" },
{ "lat": 43.577000, "lng": 2.345000, "grv": "#f6ff00" },
{ "lat": 43.712000, "lng": 2.699000, "grv": "#f6ff00" },
{ "lat": 43.586000, "lng": 2.202000, "grv": "#f6ff00" },
{ "lat": 43.657000, "lng": 2.099000, "grv": "#f6ff00" },
{ "lat": 43.577000, "lng": 2.009990, "grv": "#f6ff00" },
{ "lat": 43.871000, "lng": 2.250000, "grv": "#f6ff00" },
{ "lat": 43.259000, "lng": 2.265000, "grv": "#ffae00" },
{ "lat": 43.287000, "lng": 2.007000, "grv": "#ffae00" },
{ "lat": 43.178000, "lng": 2.656000, "grv": "#ffae00" },
{ "lat": 43.200000, "lng": 2.460000, "grv": "#ffae00" },
{ "lat": 43.793000, "lng": 2.939000, "grv": "#ffae00" },
{ "lat": 43.805000, "lng": 2.184000, "grv": "#ffae00" },
{ "lat": 43.870000, "lng": 2.187000, "grv": "#ffae00" },
{ "lat": 43.921000, "lng": 2.083000, "grv": "#ffae00" },
{ "lat": 43.522400, "lng": 2.133140, "grv": "#ffae00" },
{ "lat": 43.080000, "lng": 2.190000, "grv": "#ffae00" },
{ "lat": 43.270000, "lng": 2.750000, "grv": "#ffae00" },
{ "lat": 43.444000, "lng": 2.918000, "grv": "#ffae00" },
{ "lat": 43.248000, "lng": 2.663000, "grv": "#ffae00" },
{ "lat": 43.300000, "lng": 2.540000, "grv": "#ffae00" },
{ "lat": 43.203000, "lng": 2.147000, "grv": "#ffae00" },
{ "lat": 43.223000, "lng": 2.847000, "grv": "#ffae00" },
{ "lat": 43.056000, "lng": 2.965000, "grv": "#ffae00" },
{ "lat": 43.264000, "lng": 2.227000, "grv": "#ffae00" },
{ "lat": 43.267000, "lng": 2.245000, "grv": "#ffae00" },
{ "lat": 43.366000, "lng": 2.270000, "grv": "#ffae00" },
{ "lat": 43.043000, "lng": 2.216000, "grv": "#ffae00" },
{ "lat": 43.044000, "lng": 2.254000, "grv": "#ffae00" },
{ "lat": 43.258000, "lng": 2.410000, "grv": "#ffae00" },
{ "lat": 43.208000, "lng": 2.415000, "grv": "#ffae00" },
{ "lat": 43.252000, "lng": 2.382000, "grv": "#ffae00" },
{ "lat": 43.019000, "lng": 2.975000, "grv": "#ffae00" },
{ "lat": 43.190000, "lng": 2.919000, "grv": "#ffae00" },
{ "lat": 43.043000, "lng": 2.244000, "grv": "#ffae00" },
{ "lat": 43.255000, "lng": 2.655000, "grv": "#ffae00" },
{ "lat": 43.065000, "lng": 2.670000, "grv": "#ffae00" },
{ "lat": 43.093000, "lng": 2.229000, "grv": "#ffae00" },
{ "lat": 43.171000, "lng": 2.302000, "grv": "#ffae00" },
{ "lat": 43.317000, "lng": 2.558000, "grv": "#ffae00" },
{ "lat": 43.080000, "lng": 2.689000, "grv": "#ffae00" },
{ "lat": 43.270000, "lng": 2.570000, "grv": "#ffae00" },
{ "lat": 43.277000, "lng": 2.078000, "grv": "#ffae00" },
{ "lat": 43.247000, "lng": 2.325000, "grv": "#ffae00" },
{ "lat": 43.300000, "lng": 2.455000, "grv": "#ffae00" },
{ "lat": 43.096000, "lng": 2.597000, "grv": "#ffae00" },
{ "lat": 43.310000, "lng": 2.550000, "grv": "#ffae00" },
{ "lat": 43.318000, "lng": 2.013000, "grv": "#ffae00" },
{ "lat": 43.110000, "lng": 2.254000, "grv": "#ffae00" },
{ "lat": 43.102000, "lng": 2.500000, "grv": "#ffae00" },
{ "lat": 43.232000, "lng": 2.639000, "grv": "#ffae00" },
{ "lat": 43.226000, "lng": 2.619000, "grv": "#ffae00" },
{ "lat": 43.314000, "lng": 2.491000, "grv": "#ffae00" },
{ "lat": 43.216000, "lng": 2.539000, "grv": "#ffae00" },
{ "lat": 43.239000, "lng": 2.257000, "grv": "#ffae00" },
{ "lat": 43.314000, "lng": 2.493000, "grv": "#ffae00" },
{ "lat": 43.313000, "lng": 2.341000, "grv": "#ffae00" },
{ "lat": 43.332000, "lng": 2.026000, "grv": "#ffae00" },
{ "lat": 43.058000, "lng": 2.214000, "grv": "#ffae00" },
{ "lat": 43.062000, "lng": 2.224000, "grv": "#ffae00" },
{ "lat": 43.044000, "lng": 2.287000, "grv": "#ffae00" },
{ "lat": 43.301000, "lng": 2.007000, "grv": "#ffae00" },
{ "lat": 43.270000, "lng": 2.718000, "grv": "#ffae00" },
{ "lat": 43.183000, "lng": 2.375000, "grv": "#ffae00" },
{ "lat": 43.362000, "lng": 2.178000, "grv": "#ffae00" },
{ "lat": 43.260000, "lng": 2.263000, "grv": "#ffae00" },
{ "lat": 43.280000, "lng": 2.580000, "grv": "#ffae00" },
{ "lat": 43.226000, "lng": 2.115000, "grv": "#ffae00" },
{ "lat": 43.061000, "lng": 2.226000, "grv": "#ffae00" },
{ "lat": 43.174000, "lng": 2.651000, "grv": "#ffae00" },
{ "lat": 43.132000, "lng": 2.559000, "grv": "#ffae00" },
{ "lat": 43.292000, "lng": 2.855000, "grv": "#ffae00" },
{ "lat": 43.198000, "lng": 2.305000, "grv": "#ffae00" },
{ "lat": 43.128000, "lng": 2.539000, "grv": "#ffae00" },
{ "lat": 43.296000, "lng": 2.032000, "grv": "#ffae00" },
{ "lat": 43.250000, "lng": 2.066000, "grv": "#ffae00" },
{ "lat": 43.068000, "lng": 2.218000, "grv": "#ffae00" },
{ "lat": 43.026000, "lng": 2.967000, "grv": "#ffae00" },
{ "lat": 43.278000, "lng": 2.326000, "grv": "#ffae00" },
{ "lat": 43.370000, "lng": 2.290000, "grv": "#ffae00" },
{ "lat": 43.187000, "lng": 2.272000, "grv": "#ffae00" },
{ "lat": 43.174000, "lng": 2.750000, "grv": "#ffae00" },
{ "lat": 43.265000, "lng": 2.025000, "grv": "#ffae00" },
{ "lat": 43.320000, "lng": 2.380000, "grv": "#ffae00" },
{ "lat": 43.164000, "lng": 2.458000, "grv": "#ffae00" },
{ "lat": 43.212000, "lng": 2.172000, "grv": "#ffae00" },
{ "lat": 43.293000, "lng": 2.894000, "grv": "#ffae00" },
{ "lat": 43.329000, "lng": 2.524000, "grv": "#ffae00" },
{ "lat": 43.123000, "lng": 2.807000, "grv": "#ffae00" },
{ "lat": 43.137000, "lng": 2.529000, "grv": "#ffae00" },
{ "lat": 43.204000, "lng": 2.754000, "grv": "#ffae00" },
{ "lat": 43.096000, "lng": 2.713000, "grv": "#ffae00" },
{ "lat": 43.192000, "lng": 2.556000, "grv": "#ffae00" },
{ "lat": 43.391000, "lng": 2.137000, "grv": "#ffae00" },
{ "lat": 43.067000, "lng": 2.217000, "grv": "#ffae00" },
{ "lat": 43.296000, "lng": 2.033000, "grv": "#ffae00" },
{ "lat": 43.363000, "lng": 2.178000, "grv": "#ffae00" },
{ "lat": 43.292000, "lng": 2.556000, "grv": "#ffae00" },
{ "lat": 43.197000, "lng": 2.093000, "grv": "#ffae00" },
{ "lat": 43.152000, "lng": 2.728000, "grv": "#ffae00" },
{ "lat": 43.197000, "lng": 2.340000, "grv": "#ffae00" },
{ "lat": 43.233000, "lng": 2.142000, "grv": "#ffae00" },
{ "lat": 43.285000, "lng": 2.081000, "grv": "#ffae00" },
{ "lat": 43.298000, "lng": 2.697000, "grv": "#ffae00" },
{ "lat": 43.190000, "lng": 2.480000, "grv": "#ffae00" },
{ "lat": 43.068000, "lng": 2.605000, "grv": "#ffae00" },
{ "lat": 43.226000, "lng": 2.627000, "grv": "#ffae00" },
{ "lat": 43.301000, "lng": 2.048000, "grv": "#ffae00" },
{ "lat": 43.192000, "lng": 2.559000, "grv": "#ffae00" },
{ "lat": 43.325000, "lng": 2.097000, "grv": "#ffae00" },
{ "lat": 43.046000, "lng": 2.164000, "grv": "#ffae00" },
{ "lat": 43.055000, "lng": 2.218000, "grv": "#ffae00" },
{ "lat": 43.156000, "lng": 2.979000, "grv": "#ffae00" },
{ "lat": 43.153000, "lng": 2.983000, "grv": "#ffae00" },
{ "lat": 43.150000, "lng": 2.290000, "grv": "#ffae00" },
{ "lat": 43.020000, "lng": 2.538000, "grv": "#ffae00" },
{ "lat": 43.261000, "lng": 2.181000, "grv": "#ffae00" },
{ "lat": 43.195000, "lng": 2.350000, "grv": "#ffae00" },
{ "lat": 43.243000, "lng": 2.181000, "grv": "#ffae00" },
{ "lat": 43.296000, "lng": 2.701000, "grv": "#ffae00" },
{ "lat": 43.321000, "lng": 2.983000, "grv": "#ffae00" },
{ "lat": 43.256000, "lng": 2.930000, "grv": "#ffae00" },
{ "lat": 43.158000, "lng": 2.968000, "grv": "#ffae00" },
{ "lat": 43.289000, "lng": 2.584000, "grv": "#ffae00" },
{ "lat": 43.164000, "lng": 2.729000, "grv": "#ffae00" },
{ "lat": 43.156000, "lng": 2.987000, "grv": "#ffae00" },
{ "lat": 43.322000, "lng": 2.989000, "grv": "#ffae00" },
{ "lat": 43.049000, "lng": 2.225000, "grv": "#ffae00" },
{ "lat": 43.053000, "lng": 2.882000, "grv": "#ffae00" },
{ "lat": 43.128000, "lng": 2.096000, "grv": "#ffae00" },
{ "lat": 43.157000, "lng": 2.717000, "grv": "#ffae00" },
{ "lat": 43.064000, "lng": 2.911000, "grv": "#ffae00" },
{ "lat": 43.123000, "lng": 2.655000, "grv": "#ffae00" },
{ "lat": 43.236000, "lng": 2.763000, "grv": "#ffae00" },
{ "lat": 43.153000, "lng": 2.763000, "grv": "#ffae00" },
{ "lat": 43.291000, "lng": 2.570000, "grv": "#ffae00" },
{ "lat": 43.137000, "lng": 2.734000, "grv": "#ffae00" },
{ "lat": 43.181000, "lng": 2.019000, "grv": "#ffae00" },
{ "lat": 43.160000, "lng": 2.990000, "grv": "#ffae00" },
{ "lat": 43.022000, "lng": 2.977000, "grv": "#ffae00" },
{ "lat": 43.223000, "lng": 2.864000, "grv": "#ffae00" },
{ "lat": 43.197000, "lng": 2.421000, "grv": "#ffae00" },
{ "lat": 43.234000, "lng": 2.114000, "grv": "#ffae00" },
{ "lat": 43.190000, "lng": 2.930000, "grv": "#ffae00" },
{ "lat": 43.211000, "lng": 2.885000, "grv": "#ffae00" },
{ "lat": 43.154000, "lng": 2.984000, "grv": "#ffae00" },
{ "lat": 43.300000, "lng": 2.869000, "grv": "#ffae00" },
{ "lat": 43.265000, "lng": 2.071000, "grv": "#ffae00" },
{ "lat": 43.186000, "lng": 2.783000, "grv": "#ffae00" },
{ "lat": 43.260000, "lng": 2.412000, "grv": "#ffae00" },
{ "lat": 43.202000, "lng": 2.777000, "grv": "#ffae00" },
{ "lat": 43.320000, "lng": 2.690000, "grv": "#ffae00" },
{ "lat": 43.300000, "lng": 2.314000, "grv": "#ffae00" },
{ "lat": 43.285000, "lng": 2.593000, "grv": "#ffae00" },
{ "lat": 43.209000, "lng": 2.420000, "grv": "#ffae00" },
{ "lat": 43.222000, "lng": 2.930000, "grv": "#ffae00" },
{ "lat": 43.066000, "lng": 2.225000, "grv": "#ffae00" },
{ "lat": 43.979000, "lng": 2.907000, "grv": "#ffae00" },
{ "lat": 43.881000, "lng": 2.782000, "grv": "#ffae00" },
{ "lat": 43.953000, "lng": 2.902000, "grv": "#ffae00" },
{ "lat": 43.855000, "lng": 2.838000, "grv": "#ffae00" },
{ "lat": 43.964000, "lng": 2.877000, "grv": "#ffae00" },
{ "lat": 43.960000, "lng": 2.893000, "grv": "#ffae00" },
{ "lat": 43.875000, "lng": 2.753000, "grv": "#ffae00" },
{ "lat": 43.873000, "lng": 2.893000, "grv": "#ffae00" },
{ "lat": 43.960000, "lng": 2.870000, "grv": "#ffae00" },
{ "lat": 43.882000, "lng": 2.785000, "grv": "#ffae00" },
{ "lat": 43.924000, "lng": 2.593000, "grv": "#ffae00" },
{ "lat": 43.960000, "lng": 2.884000, "grv": "#ffae00" },
{ "lat": 43.962000, "lng": 2.881000, "grv": "#ffae00" },
{ "lat": 43.788000, "lng": 2.730000, "grv": "#ffae00" },
{ "lat": 43.882000, "lng": 2.605000, "grv": "#ffae00" },
{ "lat": 43.960000, "lng": 2.880000, "grv": "#ffae00" },
{ "lat": 43.961000, "lng": 2.879000, "grv": "#ffae00" },
{ "lat": 43.966000, "lng": 2.706000, "grv": "#ffae00" },
{ "lat": 43.942000, "lng": 2.828000, "grv": "#ffae00" },
{ "lat": 43.815000, "lng": 2.602000, "grv": "#ffae00" },
{ "lat": 43.959000, "lng": 2.849000, "grv": "#ffae00" },
{ "lat": 43.881000, "lng": 2.735000, "grv": "#ffae00" },
{ "lat": 43.962000, "lng": 2.889000, "grv": "#ffae00" },
{ "lat": 43.957000, "lng": 2.835000, "grv": "#ffae00" },
{ "lat": 43.849000, "lng": 2.899000, "grv": "#ffae00" },
{ "lat": 43.958000, "lng": 2.890000, "grv": "#ffae00" },
{ "lat": 43.962000, "lng": 2.884000, "grv": "#ffae00" },
{ "lat": 43.934000, "lng": 2.733000, "grv": "#ffae00" },
{ "lat": 43.964000, "lng": 2.885000, "grv": "#ffae00" },
{ "lat": 43.741000, "lng": 2.952000, "grv": "#ffae00" },
{ "lat": 43.955000, "lng": 2.915000, "grv": "#ffae00" },
{ "lat": 43.820000, "lng": 2.755000, "grv": "#ffae00" },
{ "lat": 43.962000, "lng": 2.888000, "grv": "#ffae00" },
{ "lat": 43.991000, "lng": 2.968000, "grv": "#ffae00" },
{ "lat": 43.464000, "lng": 2.004000, "grv": "#ffae00" },
{ "lat": 43.456400, "lng": 2.002520, "grv": "#ffae00" },
{ "lat": 43.447900, "lng": 2.007450, "grv": "#ffae00" },
{ "lat": 43.270000, "lng": 2.770000, "grv": "#ffae00" },
{ "lat": 43.629000, "lng": 2.667000, "grv": "#ffae00" },
{ "lat": 43.592000, "lng": 2.704000, "grv": "#ffae00" },
{ "lat": 43.341000, "lng": 2.973000, "grv": "#ffae00" },
{ "lat": 43.482000, "lng": 2.793000, "grv": "#ffae00" },
{ "lat": 43.690000, "lng": 2.962000, "grv": "#ffae00" },
{ "lat": 43.459000, "lng": 2.897000, "grv": "#ffae00" },
{ "lat": 43.488000, "lng": 2.752000, "grv": "#ffae00" },
{ "lat": 43.359000, "lng": 2.942000, "grv": "#ffae00" },
{ "lat": 43.426000, "lng": 2.949000, "grv": "#ffae00" },
{ "lat": 43.473000, "lng": 2.822000, "grv": "#ffae00" },
{ "lat": 43.416000, "lng": 2.972000, "grv": "#ffae00" },
{ "lat": 43.317000, "lng": 2.614000, "grv": "#ffae00" },
{ "lat": 43.291000, "lng": 2.715000, "grv": "#ffae00" },
{ "lat": 43.343000, "lng": 2.610000, "grv": "#ffae00" },
{ "lat": 43.333000, "lng": 2.659000, "grv": "#ffae00" },
{ "lat": 43.600000, "lng": 2.849000, "grv": "#ffae00" },
{ "lat": 43.460000, "lng": 2.897000, "grv": "#ffae00" },
{ "lat": 43.283000, "lng": 2.760000, "grv": "#ffae00" },
{ "lat": 43.369000, "lng": 2.776000, "grv": "#ffae00" },
{ "lat": 43.360000, "lng": 2.991000, "grv": "#ffae00" },
{ "lat": 43.472000, "lng": 2.766000, "grv": "#ffae00" },
{ "lat": 43.485000, "lng": 2.793000, "grv": "#ffae00" },
{ "lat": 43.474000, "lng": 2.831000, "grv": "#ffae00" },
{ "lat": 43.355000, "lng": 2.997000, "grv": "#ffae00" },
{ "lat": 43.647230, "lng": 2.955860, "grv": "#ffae00" },
{ "lat": 43.483290, "lng": 2.751320, "grv": "#ffae00" },
{ "lat": 43.569000, "lng": 2.945000, "grv": "#ffae00" },
{ "lat": 43.473000, "lng": 2.767000, "grv": "#ffae00" },
{ "lat": 43.426850, "lng": 2.977640, "grv": "#ffae00" },
{ "lat": 43.492000, "lng": 2.762000, "grv": "#ffae00" },
{ "lat": 43.290000, "lng": 2.746000, "grv": "#ffae00" },
{ "lat": 43.439860, "lng": 2.739520, "grv": "#ffae00" },
{ "lat": 43.275710, "lng": 2.727670, "grv": "#ffae00" },
{ "lat": 43.575000, "lng": 2.989000, "grv": "#ffae00" },
{ "lat": 43.290220, "lng": 2.764130, "grv": "#ffae00" },
{ "lat": 43.469630, "lng": 2.766790, "grv": "#ffae00" },
{ "lat": 43.345680, "lng": 2.789130, "grv": "#ffae00" },
{ "lat": 43.647000, "lng": 2.051000, "grv": "#ffae00" },
{ "lat": 43.582000, "lng": 2.147000, "grv": "#ffae00" },
{ "lat": 43.914000, "lng": 2.205000, "grv": "#ffae00" },
{ "lat": 43.670000, "lng": 2.293000, "grv": "#ffae00" },
{ "lat": 43.714000, "lng": 2.700000, "grv": "#ffae00" },
{ "lat": 43.554000, "lng": 2.119000, "grv": "#ffae00" },
{ "lat": 43.716000, "lng": 2.357000, "grv": "#ffae00" },
{ "lat": 43.539000, "lng": 2.472000, "grv": "#ffae00" },
{ "lat": 43.479000, "lng": 2.506000, "grv": "#ffae00" },
{ "lat": 43.828000, "lng": 2.041000, "grv": "#ffae00" },
{ "lat": 43.550000, "lng": 2.345000, "grv": "#ffae00" },
{ "lat": 43.511000, "lng": 2.224000, "grv": "#ffae00" },
{ "lat": 43.580000, "lng": 2.140000, "grv": "#ffae00" },
{ "lat": 43.488000, "lng": 2.475000, "grv": "#ffae00" },
{ "lat": 43.920000, "lng": 2.069000, "grv": "#ffae00" },
{ "lat": 43.632000, "lng": 2.353000, "grv": "#ffae00" },
{ "lat": 43.543000, "lng": 2.260000, "grv": "#ffae00" },
{ "lat": 43.631000, "lng": 2.383000, "grv": "#ffae00" },
{ "lat": 43.522000, "lng": 2.308000, "grv": "#ffae00" },
{ "lat": 43.784000, "lng": 2.185000, "grv": "#ffae00" },
{ "lat": 43.681000, "lng": 2.157000, "grv": "#ffae00" },
{ "lat": 43.690000, "lng": 2.210000, "grv": "#ffae00" },
{ "lat": 43.498000, "lng": 2.441000, "grv": "#ffae00" },
{ "lat": 43.527000, "lng": 2.296000, "grv": "#ffae00" },
{ "lat": 43.526000, "lng": 2.364000, "grv": "#ffae00" },
{ "lat": 43.832000, "lng": 2.258000, "grv": "#ffae00" },
{ "lat": 43.688000, "lng": 2.083000, "grv": "#ffae00" },
{ "lat": 43.756000, "lng": 2.831000, "grv": "#ffae00" },
{ "lat": 43.634000, "lng": 2.103000, "grv": "#ffae00" },
{ "lat": 43.532000, "lng": 2.097000, "grv": "#ffae00" },
{ "lat": 43.544000, "lng": 2.012000, "grv": "#ffae00" },
{ "lat": 43.619000, "lng": 2.099000, "grv": "#ffae00" },
{ "lat": 43.866000, "lng": 2.562000, "grv": "#ffae00" },
{ "lat": 43.629000, "lng": 2.097000, "grv": "#ffae00" },
{ "lat": 43.535000, "lng": 2.507000, "grv": "#ffae00" },
{ "lat": 43.573000, "lng": 2.018000, "grv": "#ffae00" },
{ "lat": 43.628000, "lng": 2.141000, "grv": "#ffae00" },
{ "lat": 43.520000, "lng": 2.010000, "grv": "#ffae00" },
{ "lat": 43.899000, "lng": 2.374000, "grv": "#ffae00" },
{ "lat": 43.863000, "lng": 2.075000, "grv": "#ffae00" },
{ "lat": 43.573000, "lng": 2.019000, "grv": "#ffae00" },
{ "lat": 43.575000, "lng": 2.135000, "grv": "#ffae00" },
{ "lat": 43.729000, "lng": 2.061000, "grv": "#ffae00" },
{ "lat": 43.573000, "lng": 2.017000, "grv": "#ffae00" },
{ "lat": 43.925000, "lng": 2.018000, "grv": "#ffae00" },
{ "lat": 43.851000, "lng": 2.513000, "grv": "#ffae00" },
{ "lat": 43.701000, "lng": 2.196000, "grv": "#ffae00" },
{ "lat": 43.634000, "lng": 2.761000, "grv": "#ffae00" },
{ "lat": 43.549000, "lng": 2.120000, "grv": "#ffae00" },
{ "lat": 43.551000, "lng": 2.274000, "grv": "#ffae00" },
{ "lat": 43.541000, "lng": 2.263000, "grv": "#ffae00" },
{ "lat": 43.495000, "lng": 2.329000, "grv": "#ffae00" },
{ "lat": 43.577000, "lng": 2.006000, "grv": "#ffae00" },
{ "lat": 43.713000, "lng": 2.687000, "grv": "#ffae00" },
{ "lat": 43.510000, "lng": 2.403000, "grv": "#ffae00" },
{ "lat": 43.725000, "lng": 2.145000, "grv": "#ffae00" },
{ "lat": 43.657000, "lng": 2.035000, "grv": "#ffae00" },
{ "lat": 43.697000, "lng": 2.676000, "grv": "#ffae00" },
{ "lat": 43.526000, "lng": 2.135000, "grv": "#ffae00" },
{ "lat": 43.493000, "lng": 2.461000, "grv": "#ffae00" },
{ "lat": 43.897000, "lng": 2.002000, "grv": "#ffae00" },
{ "lat": 43.515000, "lng": 2.010000, "grv": "#ffae00" },
{ "lat": 43.791000, "lng": 2.094000, "grv": "#ffae00" },
{ "lat": 43.871000, "lng": 2.557000, "grv": "#ffae00" },
{ "lat": 43.590000, "lng": 2.174000, "grv": "#ffae00" },
{ "lat": 43.739000, "lng": 2.040000, "grv": "#ffae00" },
{ "lat": 43.466000, "lng": 2.079000, "grv": "#ffae00" },
{ "lat": 43.561000, "lng": 2.096000, "grv": "#ffae00" },
{ "lat": 43.707000, "lng": 2.136000, "grv": "#ffae00" },
{ "lat": 43.676000, "lng": 2.130000, "grv": "#ffae00" },
{ "lat": 43.595000, "lng": 2.159000, "grv": "#ffae00" },
{ "lat": 43.710000, "lng": 2.694000, "grv": "#ffae00" },
{ "lat": 43.536000, "lng": 2.283000, "grv": "#ffae00" },
{ "lat": 43.573000, "lng": 2.304000, "grv": "#ffae00" },
{ "lat": 43.509000, "lng": 2.156000, "grv": "#ffae00" },
{ "lat": 43.535000, "lng": 2.201000, "grv": "#ffae00" },
{ "lat": 43.431000, "lng": 2.058000, "grv": "#ffae00" },
{ "lat": 43.868000, "lng": 2.227000, "grv": "#ffae00" },
{ "lat": 43.479000, "lng": 2.507000, "grv": "#ffae00" },
{ "lat": 43.808000, "lng": 2.144000, "grv": "#ffae00" },
{ "lat": 43.726000, "lng": 2.143000, "grv": "#ffae00" },
{ "lat": 43.497000, "lng": 2.451000, "grv": "#ffae00" },
{ "lat": 43.516000, "lng": 2.259000, "grv": "#ffae00" },
{ "lat": 43.576000, "lng": 2.173000, "grv": "#ffae00" },
{ "lat": 43.560000, "lng": 2.280000, "grv": "#ffae00" },
{ "lat": 43.489000, "lng": 2.013000, "grv": "#ffae00" },
{ "lat": 43.576000, "lng": 2.009990, "grv": "#ffae00" },
{ "lat": 43.848000, "lng": 2.037000, "grv": "#ffae00" },
{ "lat": 43.884000, "lng": 2.231000, "grv": "#ffae00" },
{ "lat": 43.986000, "lng": 2.136000, "grv": "#ffae00" },
{ "lat": 43.723000, "lng": 2.735000, "grv": "#ffae00" },
{ "lat": 43.580000, "lng": 2.142000, "grv": "#ffae00" },
{ "lat": 43.581000, "lng": 2.112000, "grv": "#ffae00" },
{ "lat": 43.624000, "lng": 2.093990, "grv": "#ffae00" },
{ "lat": 43.698000, "lng": 2.024000, "grv": "#ffae00" },
{ "lat": 43.714000, "lng": 2.794000, "grv": "#ffae00" },
{ "lat": 43.530000, "lng": 2.359000, "grv": "#ffae00" },
{ "lat": 43.877000, "lng": 2.501000, "grv": "#ffae00" },
{ "lat": 43.562000, "lng": 2.352000, "grv": "#ffae00" },
{ "lat": 43.587000, "lng": 2.033990, "grv": "#ffae00" },
{ "lat": 43.726000, "lng": 2.069990, "grv": "#ffae00" },
{ "lat": 43.600000, "lng": 2.108000, "grv": "#ffae00" },
{ "lat": 43.497000, "lng": 2.452000, "grv": "#ffae00" },
{ "lat": 43.488000, "lng": 2.473000, "grv": "#ffae00" },
{ "lat": 43.689000, "lng": 2.857000, "grv": "#ffae00" },
{ "lat": 43.918000, "lng": 2.205000, "grv": "#ffae00" },
{ "lat": 43.713000, "lng": 2.139000, "grv": "#ffae00" },
{ "lat": 43.646000, "lng": 2.321000, "grv": "#ffae00" },
{ "lat": 43.693000, "lng": 2.171000, "grv": "#ffae00" },
{ "lat": 43.629000, "lng": 2.437000, "grv": "#ffae00" },
{ "lat": 43.480000, "lng": 2.637000, "grv": "#ffae00" },
{ "lat": 43.721000, "lng": 2.349000, "grv": "#ffae00" },
{ "lat": 43.785000, "lng": 2.104000, "grv": "#ffae00" },
{ "lat": 43.496900, "lng": 2.012580, "grv": "#ffae00" },
{ "lat": 43.718200, "lng": 2.077950, "grv": "#ffae00" },
{ "lat": 43.910000, "lng": 2.209000, "grv": "#ffae00" },
{ "lat": 43.526200, "lng": 2.294280, "grv": "#ffae00" },
{ "lat": 43.729900, "lng": 2.150600, "grv": "#ffae00" },
{ "lat": 43.641100, "lng": 2.055140, "grv": "#ffae00" },
{ "lat": 43.620000, "lng": 2.233860, "grv": "#ffae00" },
{ "lat": 43.883400, "lng": 2.532940, "grv": "#ffae00" },
{ "lat": 43.739000, "lng": 2.029110, "grv": "#ffae00" },
{ "lat": 43.509100, "lng": 2.340520, "grv": "#ffae00" },
{ "lat": 43.562900, "lng": 2.321540, "grv": "#ffae00" },
{ "lat": 43.728300, "lng": 2.309890, "grv": "#ffae00" },
{ "lat": 43.766000, "lng": 2.027140, "grv": "#ffae00" },
{ "lat": 43.573200, "lng": 2.010050, "grv": "#ffae00" },
{ "lat": 43.503700, "lng": 2.380700, "grv": "#ffae00" },
{ "lat": 43.916000, "lng": 2.029990, "grv": "#ffae00" },
{ "lat": 43.432200, "lng": 2.050540, "grv": "#ffae00" },
{ "lat": 43.770100, "lng": 2.172440, "grv": "#ffae00" },
{ "lat": 43.451500, "lng": 2.047670, "grv": "#ffae00" },
{ "lat": 43.712200, "lng": 2.743170, "grv": "#ffae00" },
{ "lat": 43.458300, "lng": 2.132890, "grv": "#ffae00" },
{ "lat": 43.773200, "lng": 2.184790, "grv": "#ffae00" },
{ "lat": 43.587700, "lng": 2.112380, "grv": "#ffae00" },
{ "lat": 43.674600, "lng": 2.778910, "grv": "#ffae00" },
{ "lat": 43.509200, "lng": 2.370390, "grv": "#ffae00" },
{ "lat": 43.517500, "lng": 2.004960, "grv": "#ffae00" },
{ "lat": 43.453000, "lng": 2.035620, "grv": "#ffae00" },
{ "lat": 43.489800, "lng": 2.013590, "grv": "#ffae00" },
{ "lat": 43.523600, "lng": 2.225130, "grv": "#ffae00" },
{ "lat": 43.236000, "lng": 2.676000, "grv": "#ffae00" },
{ "lat": 43.274000, "lng": 2.038000, "grv": "#ffae00" },
{ "lat": 43.245000, "lng": 2.128000, "grv": "#ffae00" },
{ "lat": 43.331000, "lng": 2.035000, "grv": "#ffae00" },
{ "lat": 43.131000, "lng": 2.305000, "grv": "#ffae00" },
{ "lat": 43.190000, "lng": 2.300000, "grv": "#ffae00" },
{ "lat": 43.335000, "lng": 2.037000, "grv": "#ffae00" },
{ "lat": 43.215000, "lng": 2.458000, "grv": "#ffae00" },
{ "lat": 43.282000, "lng": 2.458000, "grv": "#ffae00" },
{ "lat": 43.200000, "lng": 2.750000, "grv": "#ffae00" },
{ "lat": 43.072000, "lng": 2.610000, "grv": "#ffae00" },
{ "lat": 43.306000, "lng": 2.870000, "grv": "#ffae00" },
{ "lat": 43.964000, "lng": 2.877000, "grv": "#ffae00" },
{ "lat": 43.985000, "lng": 2.930000, "grv": "#ffae00" },
{ "lat": 43.959000, "lng": 2.579000, "grv": "#ffae00" },
{ "lat": 43.760000, "lng": 2.860000, "grv": "#ffae00" },
{ "lat": 43.910000, "lng": 2.907000, "grv": "#ffae00" },
{ "lat": 43.823000, "lng": 2.776000, "grv": "#ffae00" },
{ "lat": 43.839000, "lng": 2.916000, "grv": "#ffae00" },
{ "lat": 43.885000, "lng": 2.622000, "grv": "#ffae00" },
{ "lat": 43.902000, "lng": 2.913000, "grv": "#ffae00" },
{ "lat": 43.994000, "lng": 2.934000, "grv": "#ffae00" },
{ "lat": 43.957000, "lng": 2.923000, "grv": "#ffae00" },
{ "lat": 43.474000, "lng": 2.819000, "grv": "#ffae00" },
{ "lat": 43.309010, "lng": 2.772650, "grv": "#ffae00" },
{ "lat": 43.310870, "lng": 2.640180, "grv": "#ffae00" },
{ "lat": 43.328000, "lng": 2.606000, "grv": "#ffae00" },
{ "lat": 43.400000, "lng": 2.915000, "grv": "#ffae00" },
{ "lat": 43.778000, "lng": 2.189000, "grv": "#ffae00" },
{ "lat": 43.571000, "lng": 2.316000, "grv": "#ffae00" },
{ "lat": 43.711000, "lng": 2.255000, "grv": "#ffae00" },
{ "lat": 43.711000, "lng": 2.130000, "grv": "#ffae00" },
{ "lat": 43.480000, "lng": 2.120000, "grv": "#ffae00" },
{ "lat": 43.631000, "lng": 2.353000, "grv": "#ffae00" },
{ "lat": 43.579000, "lng": 2.063000, "grv": "#ffae00" },
{ "lat": 43.569000, "lng": 2.320000, "grv": "#ffae00" },
{ "lat": 43.566000, "lng": 2.230000, "grv": "#ffae00" },
{ "lat": 43.683000, "lng": 2.780000, "grv": "#ffae00" },
{ "lat": 43.580000, "lng": 2.030000, "grv": "#ffae00" },
{ "lat": 43.570000, "lng": 2.319000, "grv": "#ffae00" },
{ "lat": 43.860000, "lng": 2.070000, "grv": "#ffae00" },
{ "lat": 43.920000, "lng": 2.234000, "grv": "#ffae00" },
{ "lat": 43.480000, "lng": 2.494000, "grv": "#ffae00" },
{ "lat": 43.694000, "lng": 2.218000, "grv": "#ffae00" },
{ "lat": 43.584000, "lng": 2.183000, "grv": "#ffae00" },
{ "lat": 43.978000, "lng": 2.096000, "grv": "#ffae00" },
{ "lat": 43.895000, "lng": 2.159000, "grv": "#ffae00" },
{ "lat": 43.800000, "lng": 2.210000, "grv": "#ffae00" },
{ "lat": 43.466000, "lng": 2.548000, "grv": "#ffae00" },
{ "lat": 43.593000, "lng": 2.113000, "grv": "#ffae00" },
{ "lat": 43.580000, "lng": 2.027000, "grv": "#ffae00" },
{ "lat": 43.930000, "lng": 2.215000, "grv": "#ffae00" },
{ "lat": 43.984000, "lng": 2.146000, "grv": "#ffae00" },
{ "lat": 43.523000, "lng": 2.303000, "grv": "#ffae00" },
{ "lat": 43.720000, "lng": 2.819000, "grv": "#ffae00" },
{ "lat": 43.558100, "lng": 2.064290, "grv": "#ffae00" },
{ "lat": 43.720100, "lng": 2.326150, "grv": "#ffae00" },
{ "lat": 43.651000, "lng": 2.103250, "grv": "#ffae00" },
{ "lat": 43.527100, "lng": 2.095280, "grv": "#ffae00" },
{ "lat": 43.775200, "lng": 2.187890, "grv": "#ffae00" },
{ "lat": 43.897400, "lng": 2.398910, "grv": "#ffae00" },
{ "lat": 43.785300, "lng": 2.187860, "grv": "#ffae00" },
{ "lat": 43.468300, "lng": 2.365620, "grv": "#ffae00" },
{ "lat": 43.089000, "lng": 2.491000, "grv": "#ffae00" },
{ "lat": 43.242000, "lng": 2.414000, "grv": "#ffae00" },
{ "lat": 43.297000, "lng": 2.677000, "grv": "#ffae00" },
{ "lat": 43.216000, "lng": 2.267000, "grv": "#ffae00" },
{ "lat": 43.883000, "lng": 2.645000, "grv": "#ffae00" },
{ "lat": 43.878000, "lng": 2.670000, "grv": "#ffae00" },
{ "lat": 43.824000, "lng": 2.781000, "grv": "#ffae00" },
{ "lat": 43.953000, "lng": 2.900000, "grv": "#ffae00" },
{ "lat": 43.960000, "lng": 2.884000, "grv": "#ffae00" },
{ "lat": 43.903000, "lng": 2.822000, "grv": "#ffae00" },
{ "lat": 43.448000, "lng": 2.021000, "grv": "#ffae00" },
{ "lat": 43.485000, "lng": 2.788000, "grv": "#ffae00" },
{ "lat": 43.426000, "lng": 2.967000, "grv": "#ffae00" },
{ "lat": 43.309510, "lng": 2.629710, "grv": "#ffae00" },
{ "lat": 43.868000, "lng": 2.230000, "grv": "#ffae00" },
{ "lat": 43.636000, "lng": 2.283000, "grv": "#ffae00" },
{ "lat": 43.530000, "lng": 2.260000, "grv": "#ffae00" },
{ "lat": 43.991000, "lng": 2.258000, "grv": "#ffae00" },
{ "lat": 43.622000, "lng": 2.159000, "grv": "#ffae00" },
{ "lat": 43.523000, "lng": 2.359000, "grv": "#ffae00" },
{ "lat": 43.638000, "lng": 2.777000, "grv": "#ffae00" },
{ "lat": 43.723000, "lng": 2.066000, "grv": "#ffae00" },
{ "lat": 43.898600, "lng": 2.314620, "grv": "#ffae00" },
{ "lat": 43.940400, "lng": 2.381310, "grv": "#ffae00" },
{ "lat": 43.260000, "lng": 2.185000, "grv": "#ffae00" },
{ "lat": 43.283000, "lng": 2.517000, "grv": "#ffae00" },
{ "lat": 43.285000, "lng": 2.312000, "grv": "#ffae00" },
{ "lat": 43.211000, "lng": 2.954000, "grv": "#ffae00" },
{ "lat": 43.823000, "lng": 2.599000, "grv": "#ffae00" },
{ "lat": 43.493000, "lng": 2.459000, "grv": "#ffae00" },
{ "lat": 43.523000, "lng": 2.301000, "grv": "#ffae00" },
{ "lat": 43.467000, "lng": 2.007000, "grv": "#ffae00" },
{ "lat": 43.263000, "lng": 2.959000, "grv": "#ffae00" },
{ "lat": 43.277000, "lng": 2.424000, "grv": "#ffae00" },
{ "lat": 43.206000, "lng": 2.753000, "grv": "#ffae00" },
{ "lat": 43.294000, "lng": 2.357000, "grv": "#ffae00" },
{ "lat": 43.287000, "lng": 2.007000, "grv": "#ffae00" },
{ "lat": 43.156000, "lng": 2.982000, "grv": "#ffae00" },
{ "lat": 43.354000, "lng": 2.117000, "grv": "#ffae00" },
{ "lat": 43.263000, "lng": 2.249000, "grv": "#ffae00" },
{ "lat": 43.207000, "lng": 2.255000, "grv": "#ffae00" },
{ "lat": 43.261000, "lng": 2.997000, "grv": "#ffae00" },
{ "lat": 43.022000, "lng": 2.253000, "grv": "#ffae00" },
{ "lat": 43.262000, "lng": 2.143000, "grv": "#ffae00" },
{ "lat": 43.188000, "lng": 2.765000, "grv": "#ffae00" },
{ "lat": 43.305000, "lng": 2.136000, "grv": "#ffae00" },
{ "lat": 43.087000, "lng": 2.227000, "grv": "#ffae00" },
{ "lat": 43.037000, "lng": 2.959000, "grv": "#ffae00" },
{ "lat": 43.294000, "lng": 2.052000, "grv": "#ffae00" },
{ "lat": 43.190000, "lng": 2.755000, "grv": "#ffae00" },
{ "lat": 43.119000, "lng": 2.708000, "grv": "#ffae00" },
{ "lat": 43.199000, "lng": 2.759000, "grv": "#ffae00" },
{ "lat": 43.159000, "lng": 2.958000, "grv": "#ffae00" },
{ "lat": 43.996000, "lng": 2.900000, "grv": "#ffae00" },
{ "lat": 43.890000, "lng": 2.607000, "grv": "#ffae00" },
{ "lat": 43.982000, "lng": 2.966000, "grv": "#ffae00" },
{ "lat": 43.790000, "lng": 2.941000, "grv": "#ffae00" },
{ "lat": 43.878000, "lng": 2.672000, "grv": "#ffae00" },
{ "lat": 43.461000, "lng": 2.012000, "grv": "#ffae00" },
{ "lat": 43.453000, "lng": 2.007000, "grv": "#ffae00" },
{ "lat": 43.447000, "lng": 2.023000, "grv": "#ffae00" },
{ "lat": 43.458000, "lng": 2.007050, "grv": "#ffae00" },
{ "lat": 43.484000, "lng": 2.686000, "grv": "#ffae00" },
{ "lat": 43.483000, "lng": 2.668000, "grv": "#ffae00" },
{ "lat": 43.311000, "lng": 2.628000, "grv": "#ffae00" },
{ "lat": 43.483000, "lng": 2.667000, "grv": "#ffae00" },
{ "lat": 43.275110, "lng": 2.742920, "grv": "#ffae00" },
{ "lat": 43.570000, "lng": 2.030000, "grv": "#ffae00" },
{ "lat": 43.611000, "lng": 2.377000, "grv": "#ffae00" },
{ "lat": 43.710000, "lng": 2.622000, "grv": "#ffae00" },
{ "lat": 43.528000, "lng": 2.294000, "grv": "#ffae00" },
{ "lat": 43.479000, "lng": 2.507000, "grv": "#ffae00" },
{ "lat": 43.525000, "lng": 2.075000, "grv": "#ffae00" },
{ "lat": 43.924000, "lng": 2.005000, "grv": "#ffae00" },
{ "lat": 43.596000, "lng": 2.152000, "grv": "#ffae00" },
{ "lat": 43.728000, "lng": 2.072000, "grv": "#ffae00" },
{ "lat": 43.528000, "lng": 2.229000, "grv": "#ffae00" },
{ "lat": 43.925000, "lng": 2.014000, "grv": "#ffae00" },
{ "lat": 43.649000, "lng": 2.045000, "grv": "#ffae00" },
{ "lat": 43.648000, "lng": 2.048000, "grv": "#ffae00" },
{ "lat": 43.631000, "lng": 2.474000, "grv": "#ffae00" },
{ "lat": 43.737000, "lng": 2.590000, "grv": "#ffae00" },
{ "lat": 43.852000, "lng": 2.065990, "grv": "#ffae00" },
{ "lat": 43.683000, "lng": 2.848000, "grv": "#ffae00" },
{ "lat": 43.600000, "lng": 2.493000, "grv": "#ffae00" },
{ "lat": 43.501000, "lng": 2.408000, "grv": "#ffae00" },
{ "lat": 43.667000, "lng": 2.540000, "grv": "#ffae00" },
{ "lat": 43.665700, "lng": 2.231360, "grv": "#ffae00" },
{ "lat": 43.793900, "lng": 2.260390, "grv": "#ffae00" },
{ "lat": 43.627600, "lng": 2.353360, "grv": "#ffae00" },
{ "lat": 43.827900, "lng": 2.190330, "grv": "#ffae00" },
{ "lat": 43.617400, "lng": 2.211840, "grv": "#ffae00" },
{ "lat": 43.053000, "lng": 2.169000, "grv": "#ffae00" },
{ "lat": 43.095000, "lng": 2.947000, "grv": "#ffae00" },
{ "lat": 43.167000, "lng": 2.116000, "grv": "#ffae00" },
{ "lat": 43.158000, "lng": 2.970000, "grv": "#ffae00" },
{ "lat": 43.985000, "lng": 2.978000, "grv": "#ffae00" },
{ "lat": 43.868000, "lng": 2.825000, "grv": "#ffae00" },
{ "lat": 43.980000, "lng": 2.963000, "grv": "#ffae00" },
{ "lat": 43.488000, "lng": 2.024000, "grv": "#ffae00" },
{ "lat": 43.416000, "lng": 2.946000, "grv": "#ffae00" },
{ "lat": 43.478000, "lng": 2.734000, "grv": "#ffae00" },
{ "lat": 43.493000, "lng": 2.760000, "grv": "#ffae00" },
{ "lat": 43.473190, "lng": 2.873050, "grv": "#ffae00" },
{ "lat": 43.945000, "lng": 2.402000, "grv": "#ffae00" },
{ "lat": 43.754000, "lng": 2.245000, "grv": "#ffae00" },
{ "lat": 43.553000, "lng": 2.224000, "grv": "#ffae00" },
{ "lat": 43.784000, "lng": 2.094000, "grv": "#ffae00" },
{ "lat": 43.269000, "lng": 2.242000, "grv": "#ffae00" },
{ "lat": 43.428000, "lng": 2.951000, "grv": "#ffae00" },
{ "lat": 43.797900, "lng": 2.186430, "grv": "#ffae00" },
{ "lat": 43.164000, "lng": 2.854000, "grv": "#ffae00" },
{ "lat": 43.235000, "lng": 2.606000, "grv": "#ffae00" },
{ "lat": 43.417000, "lng": 2.323000, "grv": "#ffae00" },
{ "lat": 43.287000, "lng": 2.007000, "grv": "#ffae00" },
{ "lat": 43.109000, "lng": 2.320000, "grv": "#ffae00" },
{ "lat": 43.242000, "lng": 2.246000, "grv": "#ffae00" },
{ "lat": 43.197000, "lng": 2.421000, "grv": "#ffae00" },
{ "lat": 43.280280, "lng": 2.730340, "grv": "#ffae00" },
{ "lat": 43.584000, "lng": 2.149000, "grv": "#ffae00" },
{ "lat": 43.638000, "lng": 2.308000, "grv": "#ffae00" },
{ "lat": 43.637000, "lng": 2.300000, "grv": "#ffae00" },
{ "lat": 43.557200, "lng": 2.280670, "grv": "#ffae00" },
{ "lat": 43.000000, "lng": 2.250000, "grv": "#ffae00" },
{ "lat": 43.645500, "lng": 2.038740, "grv": "#ffae00" },
{ "lat": 43.911000, "lng": 2.043000, "grv": "#ffae00" },
{ "lat": 43.180000, "lng": 2.326000, "grv": "#ffae00" },
{ "lat": 43.189000, "lng": 2.510000, "grv": "#ffae00" },
{ "lat": 43.849000, "lng": 2.037000, "grv": "#ffae00" },
{ "lat": 43.413500, "lng": 2.069470, "grv": "#ffae00" },
{ "lat": 43.996100, "lng": 2.017680, "grv": "#ffae00" },
{ "lat": 43.347000, "lng": 2.799000, "grv": "#ffae00" },
{ "lat": 43.373000, "lng": 2.283000, "grv": "#ffae00" },
{ "lat": 43.321000, "lng": 2.984000, "grv": "#ffae00" },
{ "lat": 43.682000, "lng": 2.223000, "grv": "#ffae00" },
{ "lat": 43.222000, "lng": 2.220000, "grv": "#ff0000" },
{ "lat": 43.305000, "lng": 2.465000, "grv": "#ff0000" },
{ "lat": 43.060000, "lng": 2.220000, "grv": "#ff0000" },
{ "lat": 43.296000, "lng": 2.036000, "grv": "#ff0000" },
{ "lat": 43.040000, "lng": 2.953000, "grv": "#ff0000" },
{ "lat": 43.114000, "lng": 2.270000, "grv": "#ff0000" },
{ "lat": 43.283000, "lng": 2.883000, "grv": "#ff0000" },
{ "lat": 43.289000, "lng": 2.074000, "grv": "#ff0000" },
{ "lat": 43.157000, "lng": 2.875000, "grv": "#ff0000" },
{ "lat": 43.199000, "lng": 2.463000, "grv": "#ff0000" },
{ "lat": 43.195000, "lng": 2.746000, "grv": "#ff0000" },
{ "lat": 43.277000, "lng": 2.613000, "grv": "#ff0000" },
{ "lat": 43.196000, "lng": 2.819000, "grv": "#ff0000" },
{ "lat": 43.213000, "lng": 2.230000, "grv": "#ff0000" },
{ "lat": 43.328000, "lng": 2.018000, "grv": "#ff0000" },
{ "lat": 43.192000, "lng": 2.567000, "grv": "#ff0000" },
{ "lat": 43.286000, "lng": 2.591000, "grv": "#ff0000" },
{ "lat": 43.285000, "lng": 2.088000, "grv": "#ff0000" },
{ "lat": 43.053000, "lng": 2.221000, "grv": "#ff0000" },
{ "lat": 43.212000, "lng": 2.881000, "grv": "#ff0000" },
{ "lat": 43.164000, "lng": 2.114000, "grv": "#ff0000" },
{ "lat": 43.309000, "lng": 2.052000, "grv": "#ff0000" },
{ "lat": 43.066000, "lng": 2.217000, "grv": "#ff0000" },
{ "lat": 43.244000, "lng": 2.657000, "grv": "#ff0000" },
{ "lat": 43.111000, "lng": 2.168000, "grv": "#ff0000" },
{ "lat": 43.259000, "lng": 2.754000, "grv": "#ff0000" },
{ "lat": 43.059000, "lng": 2.960000, "grv": "#ff0000" },
{ "lat": 43.050000, "lng": 2.930000, "grv": "#ff0000" },
{ "lat": 43.236000, "lng": 2.676000, "grv": "#ff0000" },
{ "lat": 43.200000, "lng": 2.688000, "grv": "#ff0000" },
{ "lat": 43.115000, "lng": 2.954000, "grv": "#ff0000" },
{ "lat": 43.152000, "lng": 2.793000, "grv": "#ff0000" },
{ "lat": 43.247000, "lng": 2.924000, "grv": "#ff0000" },
{ "lat": 43.108000, "lng": 2.250000, "grv": "#ff0000" },
{ "lat": 43.842000, "lng": 2.846000, "grv": "#ff0000" },
{ "lat": 43.879000, "lng": 2.658000, "grv": "#ff0000" },
{ "lat": 43.987000, "lng": 2.530000, "grv": "#ff0000" },
{ "lat": 43.433000, "lng": 2.979000, "grv": "#ff0000" },
{ "lat": 43.437000, "lng": 2.912000, "grv": "#ff0000" },
{ "lat": 43.313000, "lng": 2.641000, "grv": "#ff0000" },
{ "lat": 43.304970, "lng": 2.606770, "grv": "#ff0000" },
{ "lat": 43.440130, "lng": 2.878050, "grv": "#ff0000" },
{ "lat": 43.420800, "lng": 2.953990, "grv": "#ff0000" },
{ "lat": 43.585470, "lng": 2.703170, "grv": "#ff0000" },
{ "lat": 43.384100, "lng": 2.936520, "grv": "#ff0000" },
{ "lat": 43.345000, "lng": 2.949000, "grv": "#ff0000" },
{ "lat": 43.469000, "lng": 2.091000, "grv": "#ff0000" },
{ "lat": 43.706000, "lng": 2.847000, "grv": "#ff0000" },
{ "lat": 43.920000, "lng": 2.124000, "grv": "#ff0000" },
{ "lat": 43.581000, "lng": 2.002000, "grv": "#ff0000" },
{ "lat": 43.539000, "lng": 2.354000, "grv": "#ff0000" },
{ "lat": 43.650000, "lng": 2.007000, "grv": "#ff0000" },
{ "lat": 43.518000, "lng": 2.388000, "grv": "#ff0000" },
{ "lat": 43.716000, "lng": 2.705000, "grv": "#ff0000" },
{ "lat": 43.736000, "lng": 2.067000, "grv": "#ff0000" },
{ "lat": 43.713000, "lng": 2.793000, "grv": "#ff0000" },
{ "lat": 43.507000, "lng": 2.013000, "grv": "#ff0000" },
{ "lat": 43.925000, "lng": 2.021000, "grv": "#ff0000" },
{ "lat": 43.457000, "lng": 2.066000, "grv": "#ff0000" },
{ "lat": 43.530000, "lng": 2.094000, "grv": "#ff0000" },
{ "lat": 43.468000, "lng": 2.083000, "grv": "#ff0000" },
{ "lat": 43.585000, "lng": 2.114000, "grv": "#ff0000" },
{ "lat": 43.668000, "lng": 2.282000, "grv": "#ff0000" },
{ "lat": 43.887000, "lng": 2.226000, "grv": "#ff0000" },
{ "lat": 43.712000, "lng": 2.690000, "grv": "#ff0000" },
{ "lat": 43.716000, "lng": 2.210000, "grv": "#ff0000" },
{ "lat": 43.589000, "lng": 2.170000, "grv": "#ff0000" },
{ "lat": 43.496000, "lng": 2.014000, "grv": "#ff0000" },
{ "lat": 43.513000, "lng": 2.011000, "grv": "#ff0000" },
{ "lat": 43.574000, "lng": 2.232000, "grv": "#ff0000" },
{ "lat": 43.521000, "lng": 2.309000, "grv": "#ff0000" },
{ "lat": 43.858000, "lng": 2.069990, "grv": "#ff0000" },
{ "lat": 43.729000, "lng": 2.053990, "grv": "#ff0000" },
{ "lat": 43.562000, "lng": 2.055000, "grv": "#ff0000" },
{ "lat": 43.782300, "lng": 2.147870, "grv": "#ff0000" },
{ "lat": 43.540500, "lng": 2.107430, "grv": "#ff0000" },
{ "lat": 43.950500, "lng": 2.127000, "grv": "#ff0000" },
{ "lat": 43.939100, "lng": 2.170750, "grv": "#ff0000" },
{ "lat": 43.897700, "lng": 2.036570, "grv": "#ff0000" },
{ "lat": 43.795400, "lng": 2.208090, "grv": "#ff0000" },
{ "lat": 43.487000, "lng": 2.464600, "grv": "#ff0000" },
{ "lat": 43.945700, "lng": 2.470850, "grv": "#ff0000" },
{ "lat": 43.919600, "lng": 2.134760, "grv": "#ff0000" },
{ "lat": 43.570700, "lng": 2.225360, "grv": "#ff0000" },
{ "lat": 43.615800, "lng": 2.268690, "grv": "#ff0000" },
{ "lat": 43.694700, "lng": 2.424560, "grv": "#ff0000" },
{ "lat": 43.801000, "lng": 2.183640, "grv": "#ff0000" },
{ "lat": 43.605100, "lng": 2.237100, "grv": "#ff0000" },
{ "lat": 43.259000, "lng": 2.038000, "grv": "#ff0000" },
{ "lat": 43.265000, "lng": 2.134000, "grv": "#ff0000" },
{ "lat": 43.280000, "lng": 2.794000, "grv": "#ff0000" },
{ "lat": 43.960000, "lng": 2.858000, "grv": "#ff0000" },
{ "lat": 43.878000, "lng": 2.663000, "grv": "#ff0000" },
{ "lat": 43.902000, "lng": 2.822000, "grv": "#ff0000" },
{ "lat": 43.643000, "lng": 2.393000, "grv": "#ff0000" },
{ "lat": 43.868000, "lng": 2.187000, "grv": "#ff0000" },
{ "lat": 43.587000, "lng": 2.196000, "grv": "#ff0000" },
{ "lat": 43.925400, "lng": 2.093980, "grv": "#ff0000" },
{ "lat": 43.627300, "lng": 2.361960, "grv": "#ff0000" },
{ "lat": 43.645000, "lng": 2.059000, "grv": "#ff0000" },
{ "lat": 43.498000, "lng": 2.437000, "grv": "#ff0000" },
{ "lat": 43.272000, "lng": 2.011000, "grv": "#ff0000" },
{ "lat": 43.171000, "lng": 2.826000, "grv": "#ff0000" },
{ "lat": 43.317000, "lng": 2.500000, "grv": "#ff0000" },
{ "lat": 43.320000, "lng": 2.977000, "grv": "#ff0000" },
{ "lat": 43.209000, "lng": 2.433000, "grv": "#ff0000" },
{ "lat": 43.260000, "lng": 2.261000, "grv": "#ff0000" },
{ "lat": 43.194000, "lng": 2.608000, "grv": "#ff0000" },
{ "lat": 43.979000, "lng": 2.962000, "grv": "#ff0000" },
{ "lat": 43.978000, "lng": 2.963000, "grv": "#ff0000" },
{ "lat": 43.453650, "lng": 2.751340, "grv": "#ff0000" },
{ "lat": 43.783000, "lng": 2.158000, "grv": "#ff0000" },
{ "lat": 43.481000, "lng": 2.660000, "grv": "#ff0000" },
{ "lat": 43.920000, "lng": 2.075000, "grv": "#ff0000" },
{ "lat": 43.629000, "lng": 2.328000, "grv": "#ff0000" },
{ "lat": 43.185000, "lng": 2.964000, "grv": "#ff0000" },
{ "lat": 43.189000, "lng": 2.491000, "grv": "#ff0000" },
{ "lat": 43.161000, "lng": 2.295000, "grv": "#ff0000" },
{ "lat": 43.652000, "lng": 2.519000, "grv": "#ff0000" },
{ "lat": 43.558100, "lng": 2.064330, "grv": "#ff0000" },
{ "lat": 43.580800, "lng": 2.232370, "grv": "#ff0000" },
{ "lat": 43.192000, "lng": 2.598000, "grv": "#ff0000" },
{ "lat": 43.941000, "lng": 2.828000, "grv": "#ff0000" },
{ "lat": 43.000000, "lng": 2.000000, "grv": "#ff0000" },
{ "lat": 43.474000, "lng": 2.535000, "grv": "#ff0000" },
{ "lat": 43.460000, "lng": 2.004000, "grv": "#ff0000" },
{ "lat": 43.207000, "lng": 2.891000, "grv": "#ff0000" },
{ "lat": 43.959100, "lng": 2.517330, "grv": "#ff0000" },
{ "lat": 43.211000, "lng": 2.807000, "grv": "#ff0000" },
{ "lat": 43.213000, "lng": 2.230000, "grv": "#ff0000" },
{ "lat": 43.800800, "lng": 2.183890, "grv": "#ff0000" },
{ "lat": 43.161000, "lng": 2.892000, "grv": "#ff0000" },
{ "lat": 43.574000, "lng": 2.135000, "grv": "#ff0000" },
{ "lat": 43.030000, "lng": 2.990000, "grv": "#ff0000" },
{ "lat": 43.297000, "lng": 2.028000, "grv": "#ff0000" },
{ "lat": 43.167000, "lng": 2.996000, "grv": "#ff0000" },
{ "lat": 43.243000, "lng": 2.654000, "grv": "#ff0000" },
{ "lat": 43.174000, "lng": 2.774000, "grv": "#ff0000" },
{ "lat": 43.212000, "lng": 2.807000, "grv": "#ff0000" },
{ "lat": 43.260000, "lng": 2.240000, "grv": "#ff0000" },
{ "lat": 43.957000, "lng": 2.897000, "grv": "#ff0000" },
{ "lat": 43.650000, "lng": 2.012000, "grv": "#ff0000" },
{ "lat": 43.718000, "lng": 2.734000, "grv": "#ff0000" },
{ "lat": 43.518000, "lng": 2.321000, "grv": "#ff0000" },
{ "lat": 43.665000, "lng": 2.025000, "grv": "#ff0000" },
{ "lat": 43.783000, "lng": 2.233000, "grv": "#ff0000" },
{ "lat": 43.925100, "lng": 2.083610, "grv": "#ff0000" },
{ "lat": 43.776700, "lng": 2.161890, "grv": "#ff0000" },
{ "lat": 43.894000, "lng": 2.381160, "grv": "#ff0000" },
{ "lat": 43.033000, "lng": 2.954000, "grv": "#ff0000" },
{ "lat": 43.244000, "lng": 2.230000, "grv": "#ff0000" },
{ "lat": 43.162000, "lng": 2.989000, "grv": "#ff0000" },
{ "lat": 43.267430, "lng": 2.754620, "grv": "#ff0000" },
{ "lat": 43.879000, "lng": 2.547000, "grv": "#ff0000" },
{ "lat": 43.926000, "lng": 2.466110, "grv": "#ff0000" },
{ "lat": 43.948000, "lng": 2.489000, "grv": "#ff0000" },
{ "lat": 43.991000, "lng": 2.967000, "grv": "#ff0000" },
{} ] }
